[
  {
    "id": "animals-001",
    "category": "animals",
    "question": "花为什么会开？",
    "age": "2-4岁",
    "tags": [
      "植物",
      "花"
    ],
    "safetyLevel": "A",
    "layer1": {
      "answer": "花是植物的“宝宝工厂”！用好看的颜色和香味邀请蜜蜂蝴蝶来帮忙传粉做种子。",
      "image": "images/animals/animals-001-layer1.webp"
    },
    "layer2": {
      "followUp": "蜜蜂来了能帮什么忙？",
      "answer": "花的里面有一种叫“花粉“的黄色小粉末。蜜蜂飞到花上面吃花蜜的时候，花粉就会沾到它毛茸茸的身上。蜜蜂飞到另一朵花上，花粉就被带过去了。两朵花的花粉碰在一起，就能长出种子来。这个过程叫“传粉”！",
      "image": "images/animals/animals-001-layer2.webp"
    },
    "layer3": {
      "followUp": "那花为什么要到春天才开？",
      "answer": "因为大部分花需要合适的温度和阳光才会开。春天天气暖了、阳光多了、雨水足了，植物就知道“该开花了”。其实不是所有花都在春天开——梅花冬天就开了，菊花秋天才开，荷花夏天开。每种花都有自己的“小闹钟”，时间到了就开花！",
      "image": "images/animals/animals-001-layer3.webp"
    },
    "science": "开花是被子植物的生殖过程。花芽分化受光周期（光敏色素感知日照长度）和温度（春化作用需低温）调控。花的功能是产生配子并完成传粉受精：雄蕊产花粉（雄配子体），雌蕊含胚珠（雌配子体）。虫媒花通过颜色（含紫外线反射图案）和花蜜吸引传粉者。受精后子房发育为果实，胚珠发育为种子。",
    "experiment": {
      "name": "花朵解剖实验",
      "steps": [
        "找一朵比较大的花（如百合或月季），仔细观察外面的花瓣",
        "轻轻掰开花瓣，看看里面有什么——能找到细细的“柱子”（雄蕊）和中间的“小棒”（雌蕊）",
        "摸摸雄蕊顶部，手指上会沾上黄黄的花粉"
      ],
      "sayToChild": "这些黄黄的粉就是花粉！蜜蜂来吃花蜜的时候会沾一身花粉，带到别的花上去。花就是用这种方法来制造种子的！",
      "materials": [
        "一朵较大的花"
      ],
      "duration": "约5分钟",
      "safetyNote": "请在大人陪伴下进行，不要让宝宝把花瓣放入嘴里",
      "experimentType": "hands-on",
      "image": "images/animals/animals-001-experiment.webp"
    },
    "ipScene": "问问兔趴在花丛里看蜜蜂忙来忙去，答答熊说：“蜜蜂是花的快递员，帮花送花粉呢！”",
    "scienceImage": "images/animals/animals-001-science.webp",
    "warmClosing": "下次看到花开了，你可以告诉大人：花在邀请蜜蜂来帮忙呢！",
    "locale": "zh-CN"
  },
  {
    "id": "animals-002",
    "category": "animals",
    "question": "蚂蚁为什么排队走？",
    "age": "2-4岁",
    "tags": [
      "蚂蚁",
      "昆虫"
    ],
    "safetyLevel": "A",
    "layer1": {
      "answer": "第一只蚂蚁找到好吃的，会在路上留下“隐形墨水”。后面的蚂蚁闻着味跟着走，就排成队啦！",
      "image": "images/animals/animals-002-layer1.webp"
    },
    "layer2": {
      "followUp": "那个“隐形墨水“是什么？",
      "answer": "蚂蚁的身体会分泌一种叫“信息素“的化学物质，就像蚂蚁的特殊香水。不同的信息素代表不同的意思：“这里有食物”、“这里危险”、“跟我走”。蚂蚁的触角就是它的鼻子，用触角闻路上的信息素就能找到正确的路！",
      "image": "images/animals/animals-002-layer2.webp"
    },
    "layer3": {
      "followUp": "如果把信息素的路擦掉会怎样？",
      "answer": "蚂蚁就会乱跑了！你可以试试用手指在蚂蚁排队的路上横着划一下，前面的蚂蚁还能继续走，但后面的蚂蚁到了被擦掉的地方就会转来转去找路。不过别担心，过一会儿它们又能重新找到路。蚂蚁团队合作的能力非常强，一只小蚂蚁能搬起比自己重50倍的东西呢！",
      "image": "images/animals/animals-002-layer3.webp"
    },
    "science": "蚂蚁通过释放信息素（pheromone）进行化学通信。觅食蚂蚁发现食源后沿途释放路径信息素（主要为烃类化合物），后续蚂蚁通过触角上的化学感受器检测信息素浓度梯度寻路。信息素具有正反馈效应：走某条路的蚂蚁越多，信息素浓度越高，吸引更多蚂蚁。信息素会自然挥发，废弃路径的信号会消失。",
    "experiment": {
      "name": "蚂蚁迷路实验",
      "steps": [
        "在户外找到一排正在排队走的蚂蚁",
        "用手指沾一点水，在蚂蚁队伍中间横着划一道水痕",
        "观察蚂蚁到了水痕处会怎么做——它们会转来转去找路"
      ],
      "sayToChild": "你看，蚂蚁到了你画的水痕那里就迷路了！因为你把它们留在路上的隐形记号冲掉了。不过别担心，它们很聪明，一会儿就能重新找到路。",
      "materials": [
        "清水"
      ],
      "duration": "约10分钟",
      "safetyNote": "请在大人陪伴下观察，轻轻看不要伤害小蚂蚁",
      "experimentType": "observation",
      "image": "images/animals/animals-002-experiment.webp"
    },
    "ipScene": "问问兔看着一长排蚂蚁说：“它们在排队买东西吗？“答答熊说：“它们在跟着前面蚂蚁留下的隐形地图走呢！”",
    "scienceImage": "images/animals/animals-002-science.webp",
    "warmClosing": "下次看到蚂蚁排队，蹲下来看看它们的隐形地图吧！",
    "locale": "zh-CN"
  },
  {
    "id": "animals-003",
    "category": "animals",
    "question": "小鸟为什么会飞？",
    "age": "2-4岁",
    "tags": [
      "鸟",
      "飞行"
    ],
    "safetyLevel": "A",
    "layer1": {
      "answer": "小鸟用力扇翅膀，把空气往下推，自己就被托上天了。就像你用力拍水身体会往上浮！",
      "image": "images/animals/animals-003-layer1.webp"
    },
    "layer2": {
      "followUp": "那为什么我扇胳膊飞不起来？",
      "answer": "因为小鸟的身体是专门为飞行设计的！它的骨头是空心的，特别轻。它的翅膀上有很多羽毛，排列得很巧妙能推动空气。而且小鸟的胸部肌肉特别发达，扇翅膀的力气很大。我们人的胳膊太短、身体太重、力气太小，所以飞不起来。",
      "image": "images/animals/animals-003-layer2.webp"
    },
    "layer3": {
      "followUp": "那老鹰为什么能不扇翅膀也飞？",
      "answer": "因为老鹰的翅膀特别长特别大，像滑翔机一样。它利用从地面升起的热气流往上飘。地面被太阳晒热了，热空气往上升，老鹰展开翅膀“骑“在热气流上，不用扇翅膀就能飞得又高又远。这种飞法叫“滑翔”，省力多了！",
      "image": "images/animals/animals-003-layer3.webp"
    },
    "science": "鸟类飞行依赖：中空骨骼（减轻体重）、飞羽的空气动力学结构（产生升力和推力）、发达的胸肌（占体重15-25%）和高效呼吸系统（气囊系统实现双重呼吸）。翼型剖面产生伯努利效应升力。大型猛禽利用热气流（thermal）盘旋上升，再滑翔下降觅食，可数小时不扇翅膀。",
    "experiment": {
      "name": "纸飞机翅膀实验",
      "steps": [
        "折一架纸飞机，让它飞起来",
        "再折一架同样的纸飞机，但把翅膀剪短一半",
        "比一比哪架飞得远——翅膀大的飞得远！"
      ],
      "sayToChild": "你看，翅膀大的纸飞机飞得更远！小鸟也是这样，它的翅膀又大又有力，能更好地推动空气让自己飞起来。",
      "materials": [
        "纸",
        "剪刀"
      ],
      "duration": "约10分钟",
      "safetyNote": "请在大人陪伴下使用剪刀",
      "experimentType": "hands-on",
      "image": "images/animals/animals-003-experiment.webp"
    },
    "ipScene": "问问兔学小鸟扇胳膊跳来跳去，答答熊说：“你需要空心的骨头和一对大翅膀才行，我们还是走路吧！”",
    "scienceImage": "images/animals/animals-003-science.webp",
    "warmClosing": "下次看到小鸟飞过，和它打个招呼吧！",
    "locale": "zh-CN"
  },
  {
    "id": "animals-004",
    "category": "animals",
    "question": "树叶为什么变黄落下来？",
    "age": "2-4岁",
    "tags": [
      "树叶",
      "季节"
    ],
    "safetyLevel": "A",
    "layer1": {
      "answer": "秋天天冷了，树把叶子里的绿色营养收回去藏好。叶子没了绿色就变黄，最后掉下来。",
      "image": "images/animals/animals-004-layer1.webp"
    },
    "layer2": {
      "followUp": "叶子里的绿色去哪了？",
      "answer": "叶子里面有一种叫“叶绿素“的绿色小画家，平时叶子绿绿的就是它的功劳。秋天树把叶绿素收回到树枝和树干里保存起来。叶绿素没了，叶子里本来就藏着的黄色和橙色就显出来了。就像擦掉黑板上的绿色粉笔字，下面的黄色底板就露出来了！",
      "image": "images/animals/animals-004-layer2.webp"
    },
    "layer3": {
      "followUp": "那为什么松树冬天不掉叶子？",
      "answer": "因为松树的叶子是细细的松针，表面有一层蜡，水分不容易散失。而且松针很耐寒，不怕冷。所以松树不需要掉叶子过冬，一年四季都是绿色的，这叫“常绿树”。掉叶子的树叫“落叶树”，它们各有各的过冬办法！",
      "image": "images/animals/animals-004-layer3.webp"
    },
    "science": "秋季日照缩短、气温下降，落叶树启动叶片脱落程序：叶柄基部形成离层→叶绿素分解回收氮磷等营养→类胡萝卜素（黄/橙）显现，部分树种合成花青素（红）→离层完全形成→叶片脱落。落叶减少冬季水分蒸发和冻害风险。常绿树（如松柏）的针叶表面积小、角质层厚、含抗冻蛋白，适应低温环境。",
    "experiment": {
      "name": "树叶变色实验",
      "steps": [
        "摘一片新鲜的绿色树叶",
        "把它放在白纸上，用硬币用力刮叶子表面",
        "看到绿色的汁液印在纸上了——这就是叶绿素！"
      ],
      "sayToChild": "这个绿绿的汁就是叶绿素！秋天到了，树会把叶绿素收回去藏好。叶绿素没有了，叶子就变成黄色和红色了。大树是在收起绿色颜料准备过冬呢！",
      "materials": [
        "新鲜绿叶",
        "白纸",
        "硬币"
      ],
      "duration": "约5分钟",
      "safetyNote": "请在大人陪伴下进行",
      "experimentType": "hands-on",
      "image": "images/animals/animals-004-experiment.webp"
    },
    "ipScene": "问问兔接住一片飘落的黄叶问：“树叶为什么要离开大树？“答答熊说：“树叶在帮大树准备过冬呢，明年春天还会长出新的！”",
    "scienceImage": "images/animals/animals-004-science.webp",
    "warmClosing": "秋天捡一片落叶送给大人，告诉他们大树在准备过冬呢！",
    "locale": "zh-CN"
  },
  {
    "id": "animals-005",
    "category": "animals",
    "question": "小狗为什么摇尾巴？",
    "age": "2-4岁",
    "tags": [
      "狗",
      "动物行为"
    ],
    "safetyLevel": "A",
    "layer1": {
      "answer": "小狗不会说话，用尾巴“说话”！摇尾巴就是说“我好开心”，就像你开心会笑一样。",
      "image": "images/animals/animals-005-layer1.webp"
    },
    "layer2": {
      "followUp": "尾巴不同的摇法代表什么？",
      "answer": "尾巴高高翘起使劲摇是“我超开心”。尾巴慢慢摇是“我有点紧张，在观察”。尾巴夹在两条腿中间是“我害怕了”。尾巴竖直不动是“我在警惕”。小狗还会用耳朵、眼神和叫声来表达心情，它们有一整套“狗狗语言“呢！",
      "image": "images/animals/animals-005-layer2.webp"
    },
    "layer3": {
      "followUp": "那猫摇尾巴也是开心吗？",
      "answer": "不是哦！猫和狗的尾巴语言完全相反。猫快速甩尾巴是“我不高兴了“或者“我烦了”。猫开心的时候尾巴会竖得高高的、微微弯着。所以如果一只猫甩尾巴，最好别去碰它。每种动物的“身体语言“都不一样，需要分别去了解呢！",
      "image": "images/animals/animals-005-layer3.webp"
    },
    "science": "犬类尾巴摇动是社交信号。研究表明尾巴偏右摇动与正面情绪（左脑激活）相关，偏左摇动与负面情绪（右脑激活）相关。尾巴位置（高/低/夹）反映自信程度和情绪状态。犬类通过视觉信号（尾巴、耳朵、姿态）、声音信号（吠叫）和嗅觉信号进行沟通。猫科动物的尾巴信号系统与犬科有本质区别。",
    "experiment": {
      "name": "动物表情观察",
      "steps": [
        "找一些不同动物表情的图片或视频（狗、猫、兔子等）",
        "和宝宝一起看看它们开心、害怕、生气时的样子有什么不同",
        "让宝宝学一学动物的表情和动作"
      ],
      "sayToChild": "你看，小狗开心的时候摇尾巴，害怕的时候夹尾巴。小猫开心的时候竖尾巴，不高兴的时候甩尾巴。每种动物说话的方式都不一样呢！你开心的时候怎么表示？",
      "materials": [
        "动物图片或视频"
      ],
      "duration": "约10分钟",
      "safetyNote": "请在大人陪伴下进行",
      "experimentType": "observation",
      "image": "images/animals/animals-005-experiment.webp"
    },
    "ipScene": "问问兔见到小狗摇尾巴，也转着身子摇屁股，答答熊笑着说：“小狗在说'你好，我喜欢你'，你也在说嘛！”",
    "scienceImage": "images/animals/animals-005-science.webp",
    "warmClosing": "下次看到小狗摇尾巴，你可以对它笑笑说你好！",
    "locale": "zh-CN"
  },
  {
    "id": "animals-006",
    "category": "animals",
    "question": "猫为什么会发出呼噜声？",
    "age": "2-4岁",
    "tags": [
      "猫",
      "动物行为"
    ],
    "safetyLevel": "A",
    "layer1": {
      "answer": "猫“呼噜呼噜”的时候是在说“我好舒服、好开心”，就像你开心时会哼歌一样。",
      "image": "images/animals/animals-006-layer1.webp"
    },
    "layer2": {
      "followUp": "猫是怎么发出呼噜声的？",
      "answer": "猫的喉咙里有一对特殊的小肌肉。当猫感到舒服的时候，大脑就让这对小肌肉快速地一松一紧、一松一紧，带动声带振动。每秒钟松紧大约25-150次，就发出了“呼噜呼噜“的声音。就像你拨动橡皮筋会发出声音一样！",
      "image": "images/animals/animals-006-layer2.webp"
    },
    "layer3": {
      "followUp": "猫只有开心的时候才呼噜吗？",
      "answer": "不是的！猫有时候不舒服或者害怕也会呼噜。科学家发现呼噜声的频率（振动速度）刚好能帮助骨头和肌肉愈合。所以猫可能在用呼噜声给自己“治疗“呢！大猫也会对小猫呼噜，告诉小猫“我在这里，你很安全”。",
      "image": "images/animals/animals-006-layer3.webp"
    },
    "science": "猫的呼噜声由喉部肌肉快速收缩（频率25-150Hz）驱动声门周期性开合产生。该频率范围恰好与促进骨密度增加和软组织修复的机械振动频率重合（25-50Hz促进骨愈合）。猫在舒适、饥饿、不适甚至临终时都可能呼噜，表明呼噜具有多种功能：社交沟通、自我安慰和自我治疗。",
    "experiment": {
      "name": "振动发声实验",
      "steps": [
        "拿一把梳子和一张薄纸",
        "把纸贴在梳子齿上，嘴巴凑近轻轻哼声",
        "感受纸在振动，发出“嗡嗡“的声音"
      ],
      "sayToChild": "你听，纸在振动发出声音了！猫的呼噜声也是这样产生的——它喉咙里的小肌肉一松一紧、一松一紧，就像纸在振动一样发出了“呼噜呼噜“的声音。",
      "materials": [
        "梳子",
        "薄纸"
      ],
      "duration": "约3分钟",
      "safetyNote": "请在大人陪伴下进行",
      "experimentType": "hands-on",
      "image": "images/animals/animals-006-experiment.webp"
    },
    "ipScene": "问问兔把耳朵贴在猫咪肚子上听呼噜声，答答熊说：“它在告诉你——它觉得很舒服很安全呢！”",
    "scienceImage": "images/animals/animals-006-science.webp",
    "warmClosing": "如果你听到猫咪呼噜，那说明它觉得很安全很舒服呢！",
    "locale": "zh-CN"
  },
  {
    "id": "animals-007",
    "category": "animals",
    "question": "鱼为什么在水里不会淹到？",
    "age": "2-4岁",
    "tags": [
      "鱼",
      "呼吸"
    ],
    "safetyLevel": "A",
    "layer1": {
      "answer": "鱼用头两边的“腮”呼吸！水流过腮的时候，腮能把水里藏着的氧气吸出来用。",
      "image": "images/animals/animals-007-layer1.webp"
    },
    "layer2": {
      "followUp": "水里面也有空气吗？",
      "answer": "有的！水里面溶解了一些氧气，只是很少很少，我们看不到。鱼的腮很厉害，能把水里的氧气拿出来。鱼不停地张嘴喝水，水从腮流过的时候氧气就被吸收了。所以你看鱼嘴巴一张一合的，就是在呼吸呢！",
      "image": "images/animals/animals-007-layer2.webp"
    },
    "layer3": {
      "followUp": "那把鱼捞出来为什么会死？",
      "answer": "因为鱼的腮只能从水里吸氧气，不能直接从空气中吸。鱼离开水以后，腮的薄膜会变干粘在一起，就没法工作了。就像你在水下不能呼吸一样，鱼在空气中也“呼吸不了”。所以鱼和我们正好相反——我们在水里会溺水，鱼在空气中会“溺气”！",
      "image": "images/animals/animals-007-layer3.webp"
    },
    "science": "鱼类通过鳃呼吸：水流经鳃丝表面密布的毛细血管，溶解氧通过逆流交换机制（血液流向与水流方向相反）高效扩散进入血液。鱼鳃的气体交换效率可达80%以上（哺乳动物肺部仅约25%）。鳃丝需保持湿润才能进行气体交换，离水后鳃丝坍塌粘连导致窒息。水中溶解氧约5-14mg/L。",
    "experiment": {
      "name": "水里的空气实验",
      "steps": [
        "倒一杯冷水放在桌上",
        "等待一段时间后观察杯壁上出现的小气泡",
        "告诉宝宝：“看，水里真的藏着空气！这些小气泡就是水里的空气跑出来了”"
      ],
      "sayToChild": "你看到杯壁上的小气泡了吗？那就是水里藏的空气！鱼的腮就像一个超级吸管，能把水里这些看不见的空气吸出来呼吸。所以鱼在水里不会淹到！",
      "materials": [
        "透明杯",
        "冷水"
      ],
      "duration": "约15分钟（等待气泡出现）",
      "safetyNote": "请在大人陪伴下进行，小心不要打翻水杯",
      "experimentType": "hands-on",
      "image": "images/animals/animals-007-experiment.webp"
    },
    "ipScene": "问问兔把头伸进水盆里憋气，冒出来后说太难了，答答熊说：“你又没有腮呀！鱼用腮呼吸水里的空气，就像你用鼻子呼吸空气一样容易！”",
    "scienceImage": "images/animals/animals-007-science.webp",
    "warmClosing": "下次看到鱼嘴巴一张一合，那是它在水里呼吸呢！",
    "locale": "zh-CN"
  },
  {
    "id": "animals-008",
    "category": "animals",
    "question": "蝴蝶以前是毛毛虫吗？",
    "age": "2-4岁",
    "tags": [
      "蝴蝶",
      "变态发育"
    ],
    "safetyLevel": "A",
    "layer1": {
      "answer": "是的！毛毛虫吃了好多叶子长胖后，给自己织个小睡袋，睡一觉醒来就变成蝴蝶了！",
      "image": "images/animals/animals-008-layer1.webp"
    },
    "layer2": {
      "followUp": "它在小睡袋里做什么？",
      "answer": "在蛹里面发生了超级神奇的事情！毛毛虫的身体会慢慢溶解掉，变成一团“细胞汤”，然后用这些材料重新组装成蝴蝶的样子——长出翅膀、长出细细的腿、长出卷卷的嘴巴。就像把乐高拆了重新拼成另一个东西一样！",
      "image": "images/animals/animals-008-layer2.webp"
    },
    "layer3": {
      "followUp": "所有的虫子都会变成蝴蝶吗？",
      "answer": "不是的。毛毛虫变成蝴蝶，这种大变身叫“完全变态”。蜜蜂、甲虫、蚊子也会这样变身。但有些虫子是慢慢变大的，比如蟋蟀和蝗虫的小宝宝长得就和大人差不多，只是小一号，一次次蜕皮慢慢长大，这叫“不完全变态”。",
      "image": "images/animals/animals-008-layer3.webp"
    },
    "science": "蝴蝶经历完全变态发育（holometabolism）四阶段：卵→幼虫（毛毛虫）→蛹→成虫。蛹期（约7-21天）幼虫组织在蛋白酶作用下组织溶解（histolysis），成虫盘（imaginal disc，幼虫期已存在的未分化细胞团）利用溶解的营养重新分化和组织化（histogenesis），形成翅膀、复眼、口器等成虫结构。约85%昆虫种类经历完全变态。",
    "experiment": {
      "name": "蝴蝶成长拼图",
      "steps": [
        "和宝宝一起画四张图：鸡蛋（卵）→毛毛虫→小睡袋（蛹）→蝴蝶",
        "按顺序排列好，讲述蝴蝶的一生",
        "让宝宝指着图片复述一遍蝴蝶的变身过程"
      ],
      "sayToChild": "蝴蝶小时候是一颗小小的卵，然后变成毛毛虫拼命吃树叶长大，接着钻进小睡袋里睡一觉，醒来就变成漂亮的蝴蝶了！是不是像变魔法？",
      "materials": [
        "纸",
        "彩色画笔"
      ],
      "duration": "约10分钟",
      "safetyNote": "请在大人陪伴下进行",
      "experimentType": "hands-on",
      "image": "images/animals/animals-008-experiment.webp"
    },
    "ipScene": "问问兔看到毛毛虫吓得跳开，答答熊说：“别怕，它正在努力吃东西长大，以后会变成漂亮的蝴蝶呢！”",
    "scienceImage": "images/animals/animals-008-science.webp",
    "warmClosing": "每只蝴蝶都是毛毛虫变的，大自然的魔法真神奇！",
    "locale": "zh-CN"
  },
  {
    "id": "animals-009",
    "category": "animals",
    "question": "为什么兔子的耳朵那么长？",
    "age": "2-4岁",
    "tags": [
      "兔子",
      "耳朵"
    ],
    "safetyLevel": "A",
    "layer1": {
      "answer": "兔子的长耳朵像两个大雷达，能听到很远的声音。",
      "image": "images/animals/animals-009-layer1.webp"
    },
    "layer2": {
      "followUp": "长耳朵听得更清楚吗？",
      "answer": "耳朵大能收更多声音，还能转来转去对准方向，像天线一样能早早听到危险赶快跑。",
      "image": "images/animals/animals-009-layer2.webp"
    },
    "layer3": {
      "followUp": "兔子的长耳朵还有别的用处吗？",
      "answer": "长耳朵还是兔子的\"空调\"！耳朵血管多，风一吹热量被带走就凉快了。一对耳朵又听声又散热，真厉害！",
      "image": "images/animals/animals-009-layer3.webp"
    },
    "science": "兔耳（长可达体长的1/3）具有双重功能：1）听觉：大耳廓增大集音面积，可独立旋转270°定位声源，听觉频率范围360Hz-42kHz，对捕食者足音极为敏感；2）体温调节：耳部密集的动静脉吻合支网络在高温时扩张增加血流量，通过对流和辐射散热，可调节体温差达2-3°C。",
    "experiment": {
      "name": "大耳朵小实验",
      "steps": [
        "让宝宝用双手捂住耳朵听远处的声音——听不太清",
        "把双手张开放在耳朵后面像大耳朵一样",
        "再听听——声音变大了！"
      ],
      "sayToChild": "手放在耳朵后面声音变大了对不对？你做了一对大耳朵！兔子的长耳朵就是这个道理，像两个大喇叭帮它收集更多声音，危险来了一下就听到了。",
      "materials": [
        "无需特殊材料"
      ],
      "duration": "约3分钟",
      "safetyNote": "请在大人陪伴下进行",
      "experimentType": "hands-on",
      "image": "images/animals/animals-009-experiment.webp"
    },
    "ipScene": "问问兔竖起长耳朵左转右转说：“我听到远处有声音！“答答熊说：“你的长耳朵就像雷达一样厉害，能听到好远好远的声音呢！”",
    "locale": "zh-CN",
    "scienceImage": "images/animals/animals-009-science.webp",
    "warmClosing": "你也可以把手放在耳朵后面试试，听得更远哦！"
  },
  {
    "id": "animals-010",
    "category": "animals",
    "question": "为什么大象的鼻子那么长？",
    "age": "2-4岁",
    "tags": [
      "大象",
      "鼻子"
    ],
    "safetyLevel": "A",
    "layer1": {
      "answer": "大象的长鼻子就像一只万能的手，能抓东西、喝水、洗澡。",
      "image": "images/animals/animals-010-layer1.webp"
    },
    "layer2": {
      "followUp": "大象用鼻子做什么？",
      "answer": "鼻子能卷树枝吃叶子，吸水喷到嘴里喝，往身上喷水洗澡，还能跟别的大象勾鼻子打招呼！",
      "image": "images/animals/animals-010-layer2.webp"
    },
    "layer3": {
      "followUp": "大象的鼻子一次能吸多少水？",
      "answer": "大象鼻子一次能吸八升水，差不多一大桶！小象刚出生不会用鼻子要学好几个月。鼻子有四万条肌肉特别灵活。",
      "image": "images/animals/animals-010-layer3.webp"
    },
    "science": "象鼻是上唇与鼻子融合而成的肌肉质器官，含约40000条肌肉（人全身约600块），无骨骼支撑，能执行精细动作（如拾取花生）和粗壮动作（如举起300kg重物）。象鼻容量约8.5L。嗅觉受体基因约2000个（人类约400个），可嗅闻数公里外的水源。",
    "experiment": {
      "name": "鼻子当手实验",
      "steps": [
        "在桌上放几颗花生或小饼干",
        "让宝宝试试不用手、只用嘴或吸管把花生吸起来——很难！",
        "讨论：大象的鼻子就像一根超级吸管加手臂，能吸能卷能喷"
      ],
      "sayToChild": "你试试不用手拿东西是不是很难？大象的鼻子就是它的超级手臂，能抓能吸能喷水，还有四万条小肌肉，比你的手还灵活呢！",
      "materials": [
        "花生或小饼干",
        "吸管"
      ],
      "duration": "约5分钟",
      "safetyNote": "请在大人陪伴下进行",
      "experimentType": "hands-on",
      "image": "images/animals/animals-010-experiment.webp"
    },
    "ipScene": "问问兔看着大象的长鼻子说：“鼻子怎么那么长呀！“答答熊说：“大象的鼻子是它的万能工具，能抓东西、喝水、洗澡，还能跟朋友勾鼻子打招呼呢！”",
    "locale": "zh-CN",
    "scienceImage": "images/animals/animals-010-science.webp",
    "warmClosing": "大象的鼻子是它的超级手臂，下次在书上看到大象和它打个招呼吧！"
  },
  {
    "id": "animals-011",
    "category": "animals",
    "question": "为什么仙人掌不怕晒？",
    "age": "3-5岁",
    "tags": [
      "仙人掌",
      "植物",
      "沙漠"
    ],
    "safetyLevel": "A",
    "layer1": {
      "answer": "仙人掌身上有厚厚的皮，肚子里存满水，不怕太阳晒。",
      "image": "images/animals/animals-011-layer1.webp"
    },
    "layer2": {
      "followUp": "仙人掌怎么在沙漠里活下来的？",
      "answer": "仙人掌有三个秘密武器：厚蜡皮防水分蒸发，胖身体存水，叶子变成刺减少水分流失。",
      "image": "images/animals/animals-011-layer2.webp"
    },
    "layer3": {
      "followUp": "仙人掌的刺是叶子变的吗？",
      "answer": "叶子变成刺几乎不蒸发水，刺还能保护不被动物啃。绿绿的胖身体其实是茎，代替叶子做光合作用呢。",
      "image": "images/animals/animals-011-layer3.webp"
    },
    "science": "仙人掌（Cactaceae）是典型的旱生植物（xerophyte），适应极端干旱环境的特征：叶退化为刺减少蒸腾面积；茎肉质化储水（含水量可达90%以上）；表皮覆厚蜡质角质层减少水分散失；采用CAM（景天酸代谢）光合途径——夜间开放气孔固定CO2、白天关闭气孔减少蒸腾。根系浅而广，可快速吸收稀少降水。",
    "experiment": {
      "name": "蜡皮防水实验",
      "steps": [
        "拿两片纸巾，一片抹上一层薄蜡（用蜡笔涂满）",
        "往两片纸巾上各滴一滴水",
        "观察：涂蜡的纸巾水珠滚来滚去不渗进去"
      ],
      "sayToChild": "涂了蜡的纸巾水进不去！仙人掌的皮就像涂了一层蜡，把身体里的水牢牢锁住不让太阳晒走。这就是它在沙漠不怕晒的秘密！",
      "materials": [
        "纸巾两张",
        "蜡笔",
        "滴管或小勺",
        "水"
      ],
      "duration": "约5分钟",
      "safetyNote": "请在大人陪伴下进行",
      "experimentType": "hands-on",
      "image": "images/animals/animals-011-experiment.webp"
    },
    "ipScene": "问问兔在沙漠图片前说：“这么热的地方怎么还有植物？“答答熊指着仙人掌说：“仙人掌穿着蜡衣服、肚子里装满水、叶子变成刺，全身都是省水的好办法！”",
    "locale": "zh-CN",
    "scienceImage": "images/animals/animals-011-science.webp",
    "warmClosing": "仙人掌在沙漠里也能活，它可真是节约用水的小能手！"
  },
  {
    "id": "animals-012",
    "category": "animals",
    "question": "含羞草为什么一碰就合上？",
    "age": "3-5岁",
    "tags": [
      "植物",
      "含羞草",
      "反应"
    ],
    "safetyLevel": "A",
    "layer1": {
      "answer": "含羞草害羞了！你一碰它就赶紧把叶子合起来保护自己。",
      "image": "images/animals/animals-012-layer1.webp"
    },
    "layer2": {
      "followUp": "它真的会害羞吗？",
      "answer": "不是真害羞。碰它时叶柄底部细胞里的水快速跑掉，叶子软了就合上了。过几分钟水回来就又张开了。",
      "image": "images/animals/animals-012-layer2.webp"
    },
    "layer3": {
      "followUp": "含羞草为什么要合叶子？",
      "answer": "这是含羞草保护自己的办法。叶子突然合上会吓走小虫子。合起来面积变小，大风大雨不容易打伤它。合叶后还露出茎上的小刺，吓跑想吃它的动物。真聪明！",
      "image": "images/animals/animals-012-layer3.webp"
    },
    "science": "含羞草（Mimosa pudica）叶柄基部叶枕细胞受触碰刺激后，电信号触发膜通透性改变，K⁺和水迅速外流导致细胞失压，引起叶片闭合。恢复需数分钟重新吸水。",
    "experiment": {
      "name": "含羞草触碰实验",
      "steps": [
        "找一盆含羞草（花店或网上可以买到）",
        "轻轻碰一下叶子看它合拢",
        "等几分钟看它重新张开，再试试碰不同的叶子"
      ],
      "sayToChild": "你一碰它就合上了！叶子里的水跑掉了叶子就软了。等水回来就又张开了。它在保护自己呢！",
      "materials": [
        "含羞草盆栽"
      ],
      "duration": "约10分钟",
      "safetyNote": "请在大人陪伴下进行",
      "experimentType": "hands-on",
      "image": "images/animals/animals-012-experiment.webp"
    },
    "ipScene": "问问兔碰了含羞草，叶子哗地合上了。问问兔吓了一跳：“它生气了？“答答熊说：“没有，它在保护自己呢，一会儿就张开了！”",
    "locale": "zh-CN",
    "scienceImage": "images/animals/animals-012-science.webp",
    "warmClosing": "轻轻碰一下含羞草，看它害羞地合上叶子，好有趣呀！"
  },
  {
    "id": "animals-013",
    "category": "animals",
    "question": "萤火虫为什么会发光？",
    "age": "3-5岁",
    "tags": [
      "萤火虫",
      "昆虫",
      "发光"
    ],
    "safetyLevel": "A",
    "layer1": {
      "answer": "萤火虫肚子里有小灯笼，自己就能发光，用来找朋友！",
      "image": "images/animals/animals-013-layer1.webp"
    },
    "layer2": {
      "followUp": "肚子里的小灯笼是什么？",
      "answer": "萤火虫肚子里有荧光素，碰到氧气就发光。这种光不烫手叫冷光。控制氧气进出就能一闪一闪的。",
      "image": "images/animals/animals-013-layer2.webp"
    },
    "layer3": {
      "followUp": "萤火虫为什么要发光找朋友？",
      "answer": "夜里太黑看不清，萤火虫用特定的闪烁节奏告诉同类“我在这里”。不同种类闪烁频率和颜色不同，像各自的暗号。它们靠闪光找到伙伴，不会认错。",
      "image": "images/animals/animals-013-layer3.webp"
    },
    "science": "萤火虫发光为生物发光（bioluminescence），荧光素在荧光素酶催化下与O₂反应产生激发态氧化荧光素，退激发时释放光子。量子效率高达98%，几乎无热量散失。",
    "experiment": {
      "name": "荧光棒观察",
      "steps": [
        "掰亮一根荧光棒",
        "摸摸它是不是不烫",
        "在暗处观察它发光——这就是冷光，和萤火虫一样不发热"
      ],
      "sayToChild": "荧光棒发光了但不烫手！萤火虫肚子里发的光也是这样的冷光。它用小灯笼在夜里找朋友呢！",
      "materials": [
        "荧光棒"
      ],
      "duration": "约5分钟",
      "safetyNote": "请在大人陪伴下进行",
      "experimentType": "observation",
      "image": "images/animals/animals-013-experiment.webp"
    },
    "ipScene": "问问兔在夏夜追萤火虫跑：“它们是飞着的小星星！“答答熊说：“萤火虫肚子里有小灯笼，一闪一闪是在找朋友呢！”",
    "locale": "zh-CN",
    "scienceImage": "images/animals/animals-013-science.webp",
    "warmClosing": "夏天的晚上看看有没有萤火虫，那是它们在用小灯笼找朋友呢！"
  },
  {
    "id": "animals-014",
    "category": "animals",
    "question": "蝌蚪是怎么变成青蛙的？",
    "age": "2-4岁",
    "tags": [
      "青蛙",
      "蝌蚪",
      "春天",
      "变态发育"
    ],
    "safetyLevel": "A",
    "layer1": {
      "answer": "蝌蚪在水里慢慢长出小腿，尾巴变短，最后变成会跳的青蛙！",
      "image": "images/animals/animals-014-layer1.webp"
    },
    "layer2": {
      "followUp": "蝌蚪的尾巴去哪了？",
      "answer": "尾巴没掉，是被身体慢慢吸收了。营养被回收去长腿和肺。先长后腿再长前腿，尾巴越来越短最后消失。",
      "image": "images/animals/animals-014-layer2.webp"
    },
    "layer3": {
      "followUp": "为什么春天池塘里蝌蚪最多？",
      "answer": "青蛙冬天冬眠，春天醒来后在池塘产卵，孵出小蝌蚪。春末夏初水温好、食物多，蝌蚪长得快。到夏天很多蝌蚪变成小青蛙跳上岸，在田里帮农民捉害虫。",
      "image": "images/animals/animals-014-layer3.webp"
    },
    "science": "蛙类为两栖动物，经历不完全变态：卵→蝌蚪（水生，鳃呼吸）→变态（甲状腺激素驱动，长肢、尾部吸收、鳃退化肺发育）→成蛙（陆生，肺和皮肤呼吸）。",
    "experiment": {
      "name": "蝌蚪观察日记",
      "steps": [
        "春天在池塘边找几只蝌蚪（或从自然教育馆获取）",
        "放在大盆里每天观察记录变化",
        "画下每周蝌蚪的样子：有没有长腿、尾巴变短没有"
      ],
      "sayToChild": "蝌蚪这周长出小后腿了！它在一点点变成青蛙。每天来看看它变了多少吧！",
      "materials": [
        "大盆或鱼缸",
        "池塘水",
        "画笔和纸"
      ],
      "duration": "约4-8周（持续观察）",
      "safetyNote": "请在大人陪伴下进行",
      "experimentType": "hands-on",
      "image": "images/animals/animals-014-experiment.webp"
    },
    "ipScene": "问问兔看着池塘里蝌蚪说：“小黑点以后变成什么？“答答熊说：“它们会长出腿、缩掉尾巴，变成会呱呱叫的青蛙哦！”",
    "locale": "zh-CN",
    "scienceImage": "images/animals/animals-014-science.webp",
    "warmClosing": "春天去池塘边看看，说不定能看到蝌蚪变青蛙的过程哦！"
  },
  {
    "id": "animals-015",
    "category": "animals",
    "question": "公鸡为什么天亮就叫？",
    "age": "2-4岁",
    "tags": [
      "公鸡",
      "农村",
      "生物钟"
    ],
    "safetyLevel": "A",
    "layer1": {
      "answer": "公鸡身体里有个小闹钟，天快亮时就叫它起来打鸣！",
      "image": "images/animals/animals-015-layer1.webp"
    },
    "layer2": {
      "followUp": "公鸡身体里真有闹钟吗？",
      "answer": "不是真闹钟，叫生物钟。公鸡大脑能感觉天快亮了就兴奋大叫。就算关在黑屋子里也差不多时间打鸣呢。",
      "image": "images/animals/animals-015-layer2.webp"
    },
    "layer3": {
      "followUp": "公鸡打鸣是在说什么？",
      "answer": "公鸡打鸣是宣布“这是我的地盘”。最有力气的先叫，其他按顺序跟着叫。打鸣还告诉母鸡和小鸡天亮了出来找虫吃。在农村公鸡曾是天然闹钟呢！",
      "image": "images/animals/animals-015-layer3.webp"
    },
    "science": "公鸡打鸣受视交叉上核调控的昼夜节律驱动，并受雄激素影响。研究表明即使在恒暗条件下公鸡仍按约24小时周期打鸣，证实内源性生物钟而非光照直接触发。",
    "experiment": {
      "name": "我的生物钟记录",
      "steps": [
        "连续三天记录自己自然醒来的时间",
        "不用闹钟看看每天是不是差不多时间醒",
        "和家人讨论：我们身体里也有小闹钟！"
      ],
      "sayToChild": "你发现不用闹钟也差不多时间醒来了吗？你身体里也有小闹钟！公鸡的小闹钟告诉它天亮该打鸣了。",
      "materials": [
        "纸和笔记录时间"
      ],
      "duration": "约3天（每天记录1分钟）",
      "safetyNote": "请在大人陪伴下进行",
      "experimentType": "observation",
      "image": "images/animals/animals-015-experiment.webp"
    },
    "ipScene": "问问兔一大早被公鸡叫醒，揉着眼睛说：“公鸡怎么知道天亮了？“答答熊说：“公鸡身体里有个小闹钟，每天天亮就响！”",
    "locale": "zh-CN",
    "scienceImage": "images/animals/animals-015-science.webp",
    "warmClosing": "明天不用闹钟试试看，你身体里也有小闹钟呢！"
  },
  {
    "id": "animals-016",
    "category": "animals",
    "question": "为什么蜗牛背着壳？",
    "age": "2-4岁",
    "tags": [
      "蜗牛",
      "动物",
      "保护"
    ],
    "safetyLevel": "A",
    "layer1": {
      "answer": "蜗牛的壳是它的小房子，遇到危险缩进去就安全啦！",
      "image": "images/animals/animals-016-layer1.webp"
    },
    "layer2": {
      "followUp": "蜗牛的壳是怎么长出来的？",
      "answer": "蜗牛一出生就有壳，吃的食物里有钙，身体用钙一圈圈把壳加厚加大。蜗牛长大壳也跟着长大。",
      "image": "images/animals/animals-016-layer2.webp"
    },
    "layer3": {
      "followUp": "蜗牛能离开壳吗？",
      "answer": "不能！壳和身体连在一起，壳里有心脏和肺。壳上螺旋纹像年轮，一圈代表长大一点。壳还防止水分蒸发，天热蜗牛就缩进壳里休息。",
      "image": "images/animals/animals-016-layer3.webp"
    },
    "science": "蜗牛壳由外套膜分泌碳酸钙形成，螺旋状生长，不可脱离。壳提供物理防护、防失水和内脏保护功能。壳旋向由单个基因决定，多数为右旋。",
    "experiment": {
      "name": "蜗牛观察",
      "steps": [
        "雨后在花园找一只蜗牛",
        "轻轻放在透明塑料盒上观察它爬行",
        "轻碰它观察缩进壳里的反应"
      ],
      "sayToChild": "蜗牛慢慢爬，肚子下面是一只大脚！你轻轻碰它就缩进小房子了。壳是它随身带着的家。",
      "materials": [
        "透明塑料盒",
        "放大镜（可选）"
      ],
      "duration": "约10分钟",
      "safetyNote": "请在大人陪伴下进行",
      "experimentType": "hands-on",
      "image": "images/animals/animals-016-experiment.webp"
    },
    "ipScene": "问问兔看蜗牛背着壳慢慢爬说：“它不累吗？“答答熊说：“壳是蜗牛的小房子，走到哪住到哪，遇到危险缩进去就安全啦！”",
    "locale": "zh-CN",
    "scienceImage": "images/animals/animals-016-science.webp",
    "warmClosing": "蜗牛的壳是它的小房子，走到哪都不怕下雨呢！"
  },
  {
    "id": "animals-017",
    "category": "animals",
    "question": "为什么有的小朋友跟我不一样？",
    "age": "4-6岁",
    "tags": [
      "多样性",
      "社会情感",
      "包容"
    ],
    "safetyLevel": "A",
    "layer1": {
      "answer": "因为每个人都是独一无二的呀！不一样才让世界丰富多彩。",
      "image": "images/animals/animals-017-layer1.webp"
    },
    "layer2": {
      "followUp": "为什么有人皮肤颜色不一样、说话不一样？",
      "answer": "像花园里红花黄花紫花都漂亮。人也一样，皮肤深浅、说的话、走路方式不同，这些不一样都很好。",
      "image": "images/animals/animals-017-layer2.webp"
    },
    "layer3": {
      "followUp": "那我该怎么和不一样的小朋友相处？",
      "answer": "友善和好奇是最好的办法。不了解的事可以礼貌地问问。每个人都有擅长的和不擅长的，互相帮助就能做到一个人做不到的事。不一样不是奇怪，是世界送给我们的礼物。",
      "image": "images/animals/animals-017-layer3.webp"
    },
    "science": "人类表型多样性（肤色、语言、能力等）源于基因多态性和环境交互。认知神经科学研究表明，儿童在4-6岁开始注意社会差异，此阶段引导包容认知有助于建立终身共情能力。",
    "experiment": {
      "name": "我们的不一样真好",
      "steps": [
        "每人在纸上画自己的手掌轮廓",
        "在手掌里写或画自己最喜欢的东西和最擅长的事",
        "把大家的手掌拼在一起看——每只手都不一样，拼在一起最好看"
      ],
      "sayToChild": "每个人的手掌、喜欢的东西都不一样。拼在一起就变成最美的画！人和人不一样，才能一起做出更棒的事。",
      "materials": [
        "纸",
        "彩色画笔"
      ],
      "duration": "约15分钟",
      "safetyNote": "请在大人陪伴下进行",
      "experimentType": "hands-on",
      "image": "images/animals/animals-017-experiment.webp"
    },
    "ipScene": "问问兔遇到一只和它长得不一样的小兔子，有点犹豫。答答熊温柔地说：“你们不一样才好呀，你会跳高它会挖洞，一起玩能发现更多好玩的事！”",
    "locale": "zh-CN",
    "scienceImage": "images/animals/animals-017-science.webp",
    "warmClosing": "每个人都不一样，这才让世界变得丰富多彩呀！"
  },
  {
    "id": "animals-018",
    "category": "animals",
    "question": "为什么变色龙会变颜色？",
    "age": "3-5岁",
    "tags": [
      "变色龙",
      "动物",
      "伪装"
    ],
    "safetyLevel": "A",
    "layer1": {
      "answer": "变色龙皮肤里有好多小彩色袋子，它可以控制这些小袋子变大变小，颜色就变了！",
      "image": "images/animals/animals-018-layer1.webp"
    },
    "layer2": {
      "followUp": "变色龙为什么要变颜色？",
      "answer": "变颜色有好几个用处！变成和树叶一样的绿色可以躲起来不被发现。和其他变色龙聊天也用颜色——亮色表示“我很厉害”，深色表示“我不开心”。",
      "image": "images/animals/animals-018-layer2.webp"
    },
    "layer3": {
      "followUp": "变色龙能变成任何颜色吗？",
      "answer": "不能变成任何颜色。变色龙皮肤里有一种特殊的纳米晶体，通过调节晶体的间距来反射不同颜色的光。每种变色龙能变的颜色范围不同，不能变出自己没有的颜色。",
      "image": "images/animals/animals-018-layer3.webp"
    },
    "science": "变色龙变色不依赖色素扩散，而是通过调节皮肤中虹色细胞层内的鸟嘌呤纳米晶体间距实现：放松时晶体紧密排列反射短波长蓝光，兴奋时晶体间距增大反射长波长红/黄光。变色功能包括伪装、温度调节和社交信号。",
    "experiment": {
      "name": "颜色伪装实验",
      "steps": [
        "剪几只同样大小的纸蝴蝶，涂上不同颜色",
        "把它们放在不同颜色的背景上（绿色放绿纸、红色放红纸等）",
        "看看哪只蝴蝶最难被发现——颜色和背景一样的最难找"
      ],
      "sayToChild": "绿色蝴蝶放在绿色纸上几乎看不见了！变色龙就是这样把自己的颜色变得和周围一样来躲藏的。",
      "materials": [
        "彩色纸",
        "剪刀",
        "画笔"
      ],
      "duration": "约10分钟",
      "safetyNote": "请在大人陪伴下进行",
      "experimentType": "hands-on",
      "image": "images/animals/animals-018-experiment.webp"
    },
    "ipScene": "问问兔在树上找变色龙怎么都找不到，答答熊指着一片“树叶“说：“它就在这里呢，它把自己变成了树叶的颜色！”",
    "scienceImage": "images/animals/animals-018-science.webp",
    "warmClosing": "变色龙是大自然的伪装大师，下次在书上看到它试试能不能找到！",
    "locale": "zh-CN"
  },
  {
    "id": "animals-019",
    "category": "animals",
    "question": "为什么企鹅不怕冷？",
    "age": "3-5岁",
    "tags": [
      "企鹅",
      "南极",
      "保暖"
    ],
    "safetyLevel": "A",
    "layer1": {
      "answer": "企鹅穿着厚厚的“羽绒服”，身上的羽毛又密又防水，里面还有厚厚的脂肪保暖。",
      "image": "images/animals/animals-019-layer1.webp"
    },
    "layer2": {
      "followUp": "企鹅的羽毛和普通鸟的一样吗？",
      "answer": "不一样！企鹅的羽毛特别密，每平方厘米有一百多根，比其他鸟多好几倍。羽毛外面有油脂防水，里面有绒毛保暖，风雪都穿不透。",
      "image": "images/animals/animals-019-layer2.webp"
    },
    "layer3": {
      "followUp": "企鹅还有什么御寒本领？",
      "answer": "企鹅脚掌有特殊的血管结构，热血和冷血在脚里交换热量，这样脚不会冻伤。冬天企鹅还会几百只挤在一起抱团取暖，外面的慢慢转到里面，大家轮流暖和。",
      "image": "images/animals/animals-019-layer3.webp"
    },
    "science": "企鹅适应极寒环境的机制：1）超高密度羽毛（约100根/cm²）形成防水保温层；2）皮下脂肪层厚达2-3cm提供隔热；3）足部逆流热交换系统（动脉包裹静脉）减少热量散失；4）群体拥抱行为（huddling）可将核心温度维持在37°C，外界温度可低至-40°C。",
    "experiment": {
      "name": "羽绒保暖实验",
      "steps": [
        "拿两个塑料杯分别装满温水",
        "一个杯子用棉花或旧羽绒厚厚地包起来，另一个不包",
        "过十分钟摸摸两杯水——包着的那杯还是温的！"
      ],
      "sayToChild": "包了棉花的水还是暖的！企鹅的羽毛和脂肪就像厚厚的棉花，把身体的热量牢牢保住。所以它们在冰天雪地里也不怕冷！",
      "materials": [
        "塑料杯两个",
        "棉花或旧羽绒",
        "温水"
      ],
      "duration": "约15分钟",
      "safetyNote": "请在大人陪伴下进行",
      "experimentType": "hands-on",
      "image": "images/animals/animals-019-experiment.webp"
    },
    "ipScene": "问问兔看企鹅站在冰上打了个哆嗦：“它们不冷吗？“答答熊说：“企鹅有超厚的羽绒服和脂肪，还会抱团取暖，南极的冷风也吹不透！”",
    "scienceImage": "images/animals/animals-019-science.webp",
    "warmClosing": "企鹅挤在一起轮流取暖，团结的力量真大呀！",
    "locale": "zh-CN"
  },
  {
    "id": "animals-020",
    "category": "animals",
    "question": "为什么蜘蛛会织网？",
    "age": "3-5岁",
    "tags": [
      "蜘蛛",
      "昆虫",
      "生存"
    ],
    "safetyLevel": "A",
    "layer1": {
      "answer": "蜘蛛织网是为了捉虫子吃！网黏黏的，小虫飞过来就被粘住了。",
      "image": "images/animals/animals-020-layer1.webp"
    },
    "layer2": {
      "followUp": "蜘蛛丝是从哪里来的？",
      "answer": "蜘蛛肚子后面有吐丝器，能把身体里的蛋白质变成液体挤出来，碰到空气就变成细细的丝。蜘蛛丝比同样粗细的钢丝还结实呢！",
      "image": "images/animals/animals-020-layer2.webp"
    },
    "layer3": {
      "followUp": "蜘蛛自己不会被网粘住吗？",
      "answer": "蜘蛛真聪明！网上有的丝黏有的不黏，蜘蛛只走不黏的丝。而且蜘蛛脚上有油脂，碰到黏丝也不容易被粘。蜘蛛还记得哪根丝黏哪根不黏，像走迷宫一样熟练。",
      "image": "images/animals/animals-020-layer3.webp"
    },
    "science": "蜘蛛丝由腹部丝腺分泌的丝蛋白（spidroin）经纺丝器挤出后凝固而成。丝的抗拉强度可达1.1GPa（超过同等直径钢丝），断裂伸长率约30%。圆网蛛的网由非粘性辐丝和粘性螺旋丝构成，蜘蛛仅踏辐丝避免被粘。脚上的特殊鬃毛和油脂也有防粘作用。",
    "experiment": {
      "name": "蜘蛛网观察",
      "steps": [
        "清晨去花园或公园找一张蜘蛛网（上面可能有露珠更好看）",
        "仔细观察网的结构——中间有放射状的线，外面有圆圈状的线",
        "轻轻碰一下网的边缘，看看蜘蛛有什么反应"
      ],
      "sayToChild": "你看蜘蛛网多漂亮！中间的直线像公路，外面的圆圈线上有黏黏的胶。小虫子飞到圆圈线上就被粘住了，蜘蛛沿着不黏的直线公路跑过去吃饭！",
      "materials": [
        "放大镜（可选）"
      ],
      "duration": "约10分钟",
      "safetyNote": "请在大人陪伴下进行",
      "experimentType": "hands-on",
      "image": "images/animals/animals-020-experiment.webp"
    },
    "ipScene": "问问兔差点走进蜘蛛网，答答熊拉住它说：“这是蜘蛛的餐桌呀！它的丝比钢丝还结实，不要弄坏人家的饭碗！”",
    "scienceImage": "images/animals/animals-020-science.webp",
    "warmClosing": "蜘蛛是了不起的建筑师，它的网又美又结实！",
    "locale": "zh-CN"
  },
  {
    "id": "animals-021",
    "category": "animals",
    "question": "为什么北极熊是白色的？",
    "age": "2-4岁",
    "tags": [
      "北极熊",
      "保护色",
      "北极"
    ],
    "safetyLevel": "A",
    "layer1": {
      "answer": "北极熊住在白白的冰雪世界里，白色的毛让它和雪融为一体不容易被发现。",
      "image": "images/animals/animals-021-layer1.webp"
    },
    "layer2": {
      "followUp": "北极熊的毛真的是白色的吗？",
      "answer": "说出来你可能不信——北极熊的毛其实是透明的！每根毛是空心的小管子，光照进去反射出来看起来就是白色。就像很多透明冰块堆在一起看起来是白色一样。",
      "image": "images/animals/animals-021-layer2.webp"
    },
    "layer3": {
      "followUp": "北极熊的皮肤是什么颜色？",
      "answer": "北极熊透明毛下面的皮肤其实是黑色的！黑色皮肤能吸收更多太阳热量帮它保暖。透明空心的毛能让阳光穿过照到黑皮肤上。所以北极熊看起来白、皮肤黑，里外配合保暖又隐身！",
      "image": "images/animals/animals-021-layer3.webp"
    },
    "science": "北极熊毛发为中空透明的角蛋白纤维，对可见光的散射使其外观呈白色（类似雪的原理）。黑色皮肤富含黑色素，可吸收紫外线和可见光转化为热能。中空毛发具有良好隔热性能。保护色（cryptic coloration）使北极熊在冰雪环境中捕猎时不易被猎物发现。",
    "experiment": {
      "name": "透明变白实验",
      "steps": [
        "拿一根透明的吸管——它是透明的",
        "把好多根透明吸管捆在一起看——变白了！",
        "告诉宝宝北极熊的毛也是这样，一根是透明的，很多根在一起就变白了"
      ],
      "sayToChild": "一根吸管是透明的，好多根在一起就变白了！北极熊的毛也是这样，每根毛其实是透明的空心管子，很多根在一起看起来就是白色的。",
      "materials": [
        "透明吸管若干"
      ],
      "duration": "约5分钟",
      "safetyNote": "请在大人陪伴下进行",
      "experimentType": "hands-on",
      "image": "images/animals/animals-021-experiment.webp"
    },
    "ipScene": "问问兔指着图片说：“北极熊和雪一个颜色！“答答熊说：“它的毛其实是透明的呢，像冰一样，好多根在一起就变白了，这样在雪地里别人看不见它！”",
    "scienceImage": "images/animals/animals-021-science.webp",
    "warmClosing": "北极熊看起来白、皮肤却是黑的，大自然的设计真奇妙！",
    "locale": "zh-CN"
  },
  {
    "id": "animals-022",
    "category": "animals",
    "question": "为什么鹦鹉会学说话？",
    "age": "3-5岁",
    "tags": [
      "鹦鹉",
      "鸟类",
      "模仿"
    ],
    "safetyLevel": "A",
    "layer1": {
      "answer": "鹦鹉的舌头又厚又灵活，喉咙构造特别，能模仿听到的声音，包括人说话的声音！",
      "image": "images/animals/animals-022-layer1.webp"
    },
    "layer2": {
      "followUp": "鹦鹉听得懂它说的话吗？",
      "answer": "大部分鹦鹉只是模仿声音，并不真的懂意思。但有些特别聪明的鹦鹉能学会把词和东西对应起来，比如看到苹果说“苹果”。",
      "image": "images/animals/animals-022-layer2.webp"
    },
    "layer3": {
      "followUp": "为什么别的鸟不会学说话？",
      "answer": "鹦鹉大脑里有一个特殊区域专门管模仿声音，其他鸟没有这个区域或者不够发达。鹦鹉在野外就喜欢互相模仿叫声来交流，养在家里就模仿人的声音了。八哥和鹩哥也能学说话。",
      "image": "images/animals/animals-022-layer3.webp"
    },
    "science": "鹦鹉学语依赖其独特的发声学习能力：大脑中具有“核壳“结构的歌曲系统，类似于人类布罗卡区的功能。鹦鹉舌头肌肉发达、灵活，可调节口腔共鸣。鹦鹉目中约350种具有不同程度的声音模仿能力。灰鹦鹉Alex的研究证明部分鹦鹉可建立声音-概念关联，具有相当于4-6岁儿童的认知水平。",
    "experiment": {
      "name": "声音模仿游戏",
      "steps": [
        "和宝宝互相模仿对方说的词语",
        "试试模仿不同动物的叫声",
        "讨论：你是不是也像鹦鹉一样在模仿？学说话就是从模仿开始的"
      ],
      "sayToChild": "你也会模仿！你小时候学说话就是听大人说然后跟着说的，和鹦鹉学说话的方式很像呢。鹦鹉的舌头特别灵活，所以它模仿得特别像！",
      "materials": [
        "无需特殊材料"
      ],
      "duration": "约5分钟",
      "safetyNote": "请在大人陪伴下进行",
      "experimentType": "discussion",
      "image": "images/animals/animals-022-experiment.webp"
    },
    "ipScene": "问问兔对鹦鹉说“你好”，鹦鹉也说“你好”，问问兔吓了一跳。答答熊说：“它在模仿你呢！鹦鹉的舌头很灵活，能学会好多声音！”",
    "scienceImage": "images/animals/animals-022-science.webp",
    "warmClosing": "你学说话也是从模仿开始的，和鹦鹉一样聪明呢！",
    "locale": "zh-CN"
  },
  {
    "id": "animals-023",
    "category": "animals",
    "question": "为什么蜜蜂会蜇人？",
    "age": "3-5岁",
    "tags": [
      "蜜蜂",
      "昆虫",
      "安全"
    ],
    "safetyLevel": "A",
    "layer1": {
      "answer": "蜜蜂蜇人是为了保护自己和蜂巢，它们并不想主动攻击你。",
      "image": "images/animals/animals-023-layer1.webp"
    },
    "layer2": {
      "followUp": "蜜蜂蜇完人会怎样？",
      "answer": "蜜蜂蜇完人以后自己也会死掉。因为蜜蜂的刺上有倒钩，扎进去以后拔不出来，蜇完刺留在皮肤里，蜜蜂的一部分身体也跟着拉出来了。所以蜜蜂蜇人是用生命在保护家园。",
      "image": "images/animals/animals-023-layer2.webp"
    },
    "layer3": {
      "followUp": "怎么做才不会被蜜蜂蜇？",
      "answer": "看到蜜蜂不要慌张，不要拍打它，站着别动或者慢慢走开就好。蜜蜂怕深色衣服和香味。如果被蜇了要赶紧告诉大人处理。记住蜜蜂帮我们传粉、酿蜜，是很有用的小动物，不要故意去惹它。",
      "image": "images/animals/animals-023-layer3.webp"
    },
    "science": "蜜蜂蜇人是防御行为：工蜂的尾部螫针由产卵器特化而成，附有毒囊。蜂毒主要成分为蜂毒肽（melittin），引起疼痛和局部炎症。蜜蜂螫针有倒钩，蜇入皮肤后无法拔出，内脏随之拉出导致死亡（黄蜂的螫针无倒钩可反复蜇刺）。蜇人时释放报警信息素吸引更多工蜂防御。",
    "experiment": {
      "name": "蜜蜂安全观察",
      "steps": [
        "在花园或公园里远远地观察花上的蜜蜂",
        "看看蜜蜂是怎么从一朵花飞到另一朵花的",
        "告诉宝宝：蜜蜂在帮花传粉，我们远远看不打扰它就不会被蜇"
      ],
      "sayToChild": "你看蜜蜂正在花上忙着采蜜呢！它不会主动来找你的，只要你不去打扰它就很安全。蜜蜂帮花传粉帮我们酿蜜，是很辛苦的小工人！",
      "materials": [
        "无需特殊材料"
      ],
      "duration": "约5分钟",
      "safetyNote": "请在大人陪伴下进行，保持安全距离",
      "experimentType": "observation",
      "image": "images/animals/animals-023-experiment.webp"
    },
    "ipScene": "问问兔看到蜜蜂吓得要跑，答答熊拉住它说：“别跑别拍！你站着不动它就飞走了。蜜蜂蜇人是用生命保护家，不要去惹它们哦。”",
    "scienceImage": "images/animals/animals-023-science.webp",
    "warmClosing": "遇到蜜蜂不要慌，站着别动它就飞走了，你记住了真棒！",
    "locale": "zh-CN"
  },
  {
    "id": "animals-024",
    "category": "animals",
    "question": "为什么长颈鹿的脖子那么长？",
    "age": "2-4岁",
    "tags": [
      "长颈鹿",
      "动物",
      "进化"
    ],
    "safetyLevel": "A",
    "layer1": {
      "answer": "长颈鹿的长脖子能帮它吃到高高树顶上的叶子，别的动物够不着！",
      "image": "images/animals/animals-024-layer1.webp"
    },
    "layer2": {
      "followUp": "长颈鹿的脖子有多长？",
      "answer": "长颈鹿的脖子有两米多长，比很多大人还高！有趣的是，它的脖子虽然很长，但骨头的数量和你的一样——都只有七块，只是每块骨头都特别长。",
      "image": "images/animals/animals-024-layer2.webp"
    },
    "layer3": {
      "followUp": "长颈鹿喝水的时候怎么办？",
      "answer": "长颈鹿喝水要把前腿叉开、脖子弯下去才够得到水面，这个姿势很不方便也很危险，容易被捕食者偷袭。所以长颈鹿能很久不喝水，从树叶里获取水分。它们的心脏特别大特别有力，才能把血泵到那么高的脑袋里。",
      "image": "images/animals/animals-024-layer3.webp"
    },
    "science": "长颈鹿颈部由7节延长的颈椎组成（与人类相同），每节可长达25cm。其心脏重约11kg，血压约250/180mmHg（人类约120/80），是陆地动物中最高的，以保证血液供应至高处的大脑。颈部有特殊的血管瓣膜和奇异网（rete mirabile）防止低头时血液过快涌入大脑。",
    "experiment": {
      "name": "长脖子和短脖子",
      "steps": [
        "把一些好吃的放在高高的架子上",
        "让宝宝先不踮脚试试够——够不到",
        "然后给宝宝一根长棍子或者让宝宝站在小凳子上够到了"
      ],
      "sayToChild": "你用工具或者站高才能够到高处的东西。长颈鹿的长脖子就是它天生的工具，能吃到树顶上的叶子，别的动物都够不到！",
      "materials": [
        "高架子",
        "小零食",
        "小凳子"
      ],
      "duration": "约5分钟",
      "safetyNote": "请在大人陪伴下进行",
      "experimentType": "hands-on",
      "image": "images/animals/animals-024-experiment.webp"
    },
    "ipScene": "问问兔仰着头看长颈鹿说：“它的脖子好长呀！“答答熊说：“长颈鹿的脖子和你一样只有七块骨头，不过每块都特别长，这样它就能吃到最高的树叶啦！”",
    "scienceImage": "images/animals/animals-024-science.webp",
    "warmClosing": "长颈鹿的脖子骨头和你一样多，只是每块都很长，大自然真有趣！",
    "locale": "zh-CN"
  },
  {
    "id": "animals-025",
    "category": "animals",
    "question": "为什么猫头鹰晚上才出来？",
    "age": "3-5岁",
    "tags": [
      "猫头鹰",
      "夜行动物",
      "鸟类"
    ],
    "safetyLevel": "A",
    "layer1": {
      "answer": "猫头鹰有一双超级大眼睛，黑夜里也看得清楚，晚上出来捉老鼠吃。",
      "image": "images/animals/animals-025-layer1.webp"
    },
    "layer2": {
      "followUp": "猫头鹰的眼睛为什么这么大？",
      "answer": "大眼睛能收集更多的光，就像大窗户比小窗户更亮。猫头鹰的眼睛占头部面积很大，加上眼睛里有特殊的感光细胞，一点点星光月光就够它看清东西了。",
      "image": "images/animals/animals-025-layer2.webp"
    },
    "layer3": {
      "followUp": "猫头鹰还有什么夜间本领？",
      "answer": "猫头鹰的耳朵一高一低，能精确判断声音从哪里来。它的羽毛边缘有特殊的锯齿结构，飞的时候几乎没有声音，老鼠听不到它来了。脖子能转270度看各个方向。它是夜晚的超级猎手！",
      "image": "images/animals/animals-025-layer3.webp"
    },
    "science": "猫头鹰适应夜行的特征：1）大眼球富含视杆细胞，暗光敏感度是人类的100倍以上；2）不对称耳孔位置使其可在三维空间精确定位声源（误差<1°）；3）飞羽前缘锯齿状结构和绒毛表面消除飞行湍流噪音；4）颈部14节颈椎（人类7节）和特殊血管系统允许270°旋转。",
    "experiment": {
      "name": "黑暗中找声音",
      "steps": [
        "在房间里用布蒙住宝宝的眼睛",
        "大人在不同方向轻轻拍手或摇铃铛",
        "让宝宝指出声音从哪个方向来"
      ],
      "sayToChild": "你闭着眼睛也能听到声音从哪里来！猫头鹰的耳朵更厉害，一高一低，能在黑夜里精确找到老鼠发出的声音，然后悄悄飞过去捉住它。",
      "materials": [
        "蒙眼布",
        "铃铛或拨浪鼓"
      ],
      "duration": "约5分钟",
      "safetyNote": "请在大人陪伴下进行",
      "experimentType": "hands-on",
      "image": "images/animals/animals-025-experiment.webp"
    },
    "ipScene": "问问兔半夜听到“咕咕“声有点害怕，答答熊小声说：“那是猫头鹰在巡逻呢，它在帮忙捉老鼠保护庄稼。”",
    "scienceImage": "images/animals/animals-025-science.webp",
    "warmClosing": "猫头鹰是夜晚的小卫士，帮农民捉老鼠呢！",
    "locale": "zh-CN"
  },
  {
    "id": "animals-026",
    "category": "animals",
    "question": "为什么金鱼的记忆不只七秒？",
    "age": "4-6岁",
    "tags": [
      "金鱼",
      "记忆",
      "科学"
    ],
    "safetyLevel": "A",
    "layer1": {
      "answer": "很多人说金鱼只有七秒记忆，其实这是错的！金鱼能记住好几个月的事情呢。",
      "image": "images/animals/animals-026-layer1.webp"
    },
    "layer2": {
      "followUp": "金鱼真的能记住事情吗？",
      "answer": "科学家做过实验：训练金鱼按一个小杆子就有食物吃。金鱼学会了以后，过了好几个月还记得要按杆子。它们还能记住迷宫的路线呢！",
      "image": "images/animals/animals-026-layer2.webp"
    },
    "layer3": {
      "followUp": "那为什么大家都说金鱼只有七秒记忆？",
      "answer": "这只是一个流传很广的谣言，没有科学依据。金鱼虽然不是最聪明的动物，但记忆力至少能保持几个月。所以不要相信所有听到的说法，有些“常识“其实是错的，要像科学家一样去验证才行。",
      "image": "images/animals/animals-026-layer3.webp"
    },
    "science": "金鱼记忆远超流行谣言的7秒说法。以色列理工学院实验证明金鱼可在5个月后仍记住训练反应。鱼类具有海马体同源结构（端脑外侧/内侧pallium），支持空间学习和情景记忆。多项研究证实鱼类可习得条件反射、空间导航和社会学习，记忆保持期可达数月至数年。",
    "experiment": {
      "name": "金鱼喂食实验",
      "steps": [
        "如果家里有金鱼，每次喂食前先轻轻敲两下鱼缸",
        "连续做一周，观察金鱼是不是听到敲缸声就游过来了",
        "讨论：金鱼记住了敲缸=有食物，记忆力比七秒长多了！"
      ],
      "sayToChild": "你看金鱼听到敲缸声就游过来了！它记住了这个声音等于有好吃的。所以金鱼的记忆力其实很好，七秒记忆只是个谣言。不能随便相信没有验证过的话哦！",
      "materials": [
        "鱼缸和金鱼（如果有的话）",
        "鱼食"
      ],
      "duration": "约一周（每天1分钟）",
      "safetyNote": "请在大人陪伴下进行",
      "experimentType": "observation",
      "image": "images/animals/animals-026-experiment.webp"
    },
    "ipScene": "问问兔说金鱼只有七秒记忆好可怜，答答熊说：“那是谣言！科学家证明金鱼能记住好几个月的事呢。不能听到什么就信什么，要像科学家一样去验证！”",
    "scienceImage": "images/animals/animals-026-science.webp",
    "warmClosing": "金鱼的记忆力比大家以为的好多了，不要随便相信没验证的说法哦！",
    "locale": "zh-CN"
  },
  {
    "id": "animals-027",
    "category": "animals",
    "question": "为什么壁虎能在墙上爬？",
    "age": "3-5岁",
    "tags": [
      "壁虎",
      "动物",
      "物理"
    ],
    "safetyLevel": "A",
    "layer1": {
      "answer": "壁虎的脚底有超级多细细的小毛，能牢牢吸住墙壁，像天然的吸盘！",
      "image": "images/animals/animals-027-layer1.webp"
    },
    "layer2": {
      "followUp": "壁虎脚底的小毛有什么特别？",
      "answer": "壁虎每只脚底有几百万根比头发还细的小毛，每根小毛的末端又分出更细的分叉。这些分叉和墙壁之间产生一种微小的吸引力，几百万根加在一起就牢牢抓住了！",
      "image": "images/animals/animals-027-layer2.webp"
    },
    "layer3": {
      "followUp": "壁虎能在玻璃上爬吗？",
      "answer": "可以！壁虎几乎能在任何表面爬行，包括光滑的玻璃和天花板。科学家研究壁虎的脚还发明了超强胶带和机器人爬墙装置呢。壁虎脚的秘密叫“范德华力”，是一种物质之间的微弱吸引力。",
      "image": "images/animals/animals-027-layer3.webp"
    },
    "science": "壁虎趾垫上覆盖约50万根刚毛（setae），每根刚毛末端又分叉为数百个铲状纳米结构（spatulae，约200nm宽）。纳米级接触面积产生范德华力（van der Waals force），单根刚毛约产生20-40μN吸附力，全部刚毛可支撑约133kg重量。壁虎通过改变脚趾角度实现快速粘附和脱附。",
    "experiment": {
      "name": "吸盘挂钩实验",
      "steps": [
        "拿一个吸盘挂钩，按在光滑的玻璃或瓷砖上",
        "往挂钩上挂一个轻轻的小玩具",
        "告诉宝宝壁虎的脚就像无数个超级小的吸盘"
      ],
      "sayToChild": "吸盘紧紧吸住了墙！壁虎脚底有几百万根比头发还细的小毛，每根都像一个超级微小的吸盘。几百万个小吸盘一起工作，壁虎就能在墙上和天花板上跑来跑去了！",
      "materials": [
        "吸盘挂钩",
        "小玩具"
      ],
      "duration": "约3分钟",
      "safetyNote": "请在大人陪伴下进行",
      "experimentType": "hands-on",
      "image": "images/animals/animals-027-experiment.webp"
    },
    "ipScene": "问问兔看壁虎在天花板上跑：“它怎么不掉下来！“答答熊说：“壁虎脚底有几百万个小吸盘，牢牢吸住天花板，比蜘蛛侠还厉害！”",
    "scienceImage": "images/animals/animals-027-science.webp",
    "warmClosing": "壁虎是大自然的攀爬高手，科学家都在向它学习呢！",
    "locale": "zh-CN"
  },
  {
    "id": "animals-028",
    "category": "animals",
    "question": "海豚为什么那么聪明？",
    "age": "4-6岁",
    "tags": [
      "海豚",
      "大脑",
      "海洋"
    ],
    "safetyLevel": "A",
    "layer1": {
      "answer": "海豚的大脑很大很发达，它们会合作捉鱼、互相帮忙，还会玩游戏呢！",
      "image": "images/animals/animals-028-layer1.webp"
    },
    "layer2": {
      "followUp": "海豚有多聪明？",
      "answer": "海豚能认出镜子里的自己，能听懂人教给它的手势语言，还会给同伴起“名字”——每只海豚都有自己独特的口哨声，就像自己的名字。",
      "image": "images/animals/animals-028-layer2.webp"
    },
    "layer3": {
      "followUp": "海豚睡觉的时候怎么办？",
      "answer": "海豚在水里要不停换气呼吸，所以不能像我们一样完全睡着。它们的大脑一半睡觉、一半保持清醒，轮流休息。这样睡着的同时还能游泳和呼吸，不会沉到水底。这种半脑睡眠真的很特别！",
      "image": "images/animals/animals-028-layer3.webp"
    },
    "science": "海豚大脑体重比（EQ约4.14）在哺乳动物中仅次于人类（约7.4-7.8）。海豚具有自我认知能力（镜像测试）、社会学习、工具使用和复杂声音通信。每只海豚发展独特的标志性口哨（signature whistle）作为个体识别。海豚采用单半球慢波睡眠（USWS），轮流让一侧大脑休息，另一侧保持清醒控制呼吸和游泳。",
    "experiment": {
      "name": "镜子认识自己",
      "steps": [
        "在宝宝脸上贴一个小贴纸（不告诉宝宝在哪里）",
        "让宝宝照镜子看看能不能发现贴纸并取掉它",
        "讨论：海豚也能认出镜子里的自己，说明它们很聪明"
      ],
      "sayToChild": "你看到镜子里脸上有贴纸就去摘掉了！海豚也会这样——看到镜子里的自己，知道那是“我”。能认出镜子里的自己说明大脑很厉害，只有很少的动物能做到呢！",
      "materials": [
        "镜子",
        "小贴纸"
      ],
      "duration": "约5分钟",
      "safetyNote": "请在大人陪伴下进行",
      "experimentType": "observation",
      "image": "images/animals/animals-028-experiment.webp"
    },
    "ipScene": "问问兔看海豚表演问：“它们怎么这么厉害！“答答熊说：“海豚是最聪明的动物之一，它们会合作捉鱼、互相起名字，睡觉时还能睁着一只眼游泳呢！”",
    "scienceImage": "images/animals/animals-028-science.webp",
    "warmClosing": "海豚聪明又友善，它们在大海里也有自己的好朋友呢！",
    "locale": "zh-CN"
  },
  {
    "id": "animals-029",
    "category": "animals",
    "question": "为什么向日葵会跟着太阳转？",
    "age": "2-4岁",
    "tags": [
      "向日葵",
      "植物",
      "太阳"
    ],
    "safetyLevel": "A",
    "layer1": {
      "answer": "向日葵的小脸会跟着太阳转，早上朝东、中午朝上、傍晚朝西，像在追着太阳看！",
      "image": "images/animals/animals-029-layer1.webp"
    },
    "layer2": {
      "followUp": "向日葵是怎么转的？",
      "answer": "向日葵的茎上有一种叫“生长素“的东西。太阳照到的那一面生长素少长得慢，背着太阳的那面生长素多长得快。快的一面把慢的一面推过去，花就朝向太阳了。",
      "image": "images/animals/animals-029-layer2.webp"
    },
    "layer3": {
      "followUp": "向日葵长大了还会转吗？",
      "answer": "有趣的是，向日葵只有年轻的时候才会跟着太阳转。等花盘完全开放变成熟以后就不转了，会一直面朝东方。朝东能更早接收到早晨的阳光，吸引更多蜜蜂来传粉。",
      "image": "images/animals/animals-029-layer3.webp"
    },
    "science": "向日葵向光运动（heliotropism）机制：茎背光侧生长素（auxin）浓度高于向光侧，差异生长导致向光弯曲。此现象由昼夜节律与生长素不对称分布共同调控。成熟花盘停止旋转面朝东方：UC Davis研究表明东向花盘清晨升温更快，吸引的传粉者数量是西向花盘的5倍。",
    "experiment": {
      "name": "植物追光实验",
      "steps": [
        "把一盆小绿植放在窗台上",
        "过几天看看叶子是不是都朝着窗户方向长了",
        "转一下花盆，过几天再看——叶子又朝窗户转了"
      ],
      "sayToChild": "你看，植物的叶子都朝着有光的窗户长！向日葵也是这样追着太阳的。植物虽然不能走，但它们会慢慢转身去找阳光。",
      "materials": [
        "一盆小绿植"
      ],
      "duration": "约3-5天（持续观察）",
      "safetyNote": "请在大人陪伴下进行",
      "experimentType": "hands-on",
      "image": "images/animals/animals-029-experiment.webp"
    },
    "ipScene": "问问兔看向日葵一整天转来转去说：“它在跳转圈圈舞吗？“答答熊说：“它在追太阳呢！太阳走到哪，向日葵就朝向哪。”",
    "scienceImage": "images/animals/animals-029-science.webp",
    "warmClosing": "向日葵追着太阳转，是不是很像你追着喜欢的东西跑呀！",
    "locale": "zh-CN"
  },
  {
    "id": "animals-030",
    "category": "animals",
    "question": "为什么乌龟走得那么慢？",
    "age": "2-4岁",
    "tags": [
      "乌龟",
      "动物",
      "速度"
    ],
    "safetyLevel": "A",
    "layer1": {
      "answer": "乌龟背着重重的壳，短短的腿，当然走得慢啦！但它有壳保护，不需要跑得快。",
      "image": "images/animals/animals-030-layer1.webp"
    },
    "layer2": {
      "followUp": "乌龟不怕被追到吗？",
      "answer": "乌龟遇到危险就把头和腿缩进壳里，壳又硬又结实，大部分动物咬不动。不需要跑得快，缩起来就安全了。每种动物有不同的保命方式，兔子跑得快，乌龟壳很硬。",
      "image": "images/animals/animals-030-layer2.webp"
    },
    "layer3": {
      "followUp": "乌龟能活很久吗？",
      "answer": "乌龟是动物界最长寿的之一！有的乌龟能活一百多岁，最长寿的陆龟活了超过一百八十年。科学家认为乌龟代谢慢、心跳慢，身体消耗少，所以特别长寿。慢慢来也是一种很好的生活方式呢！",
      "image": "images/animals/animals-030-layer3.webp"
    },
    "science": "龟类行动缓慢与其生理特征相关：厚重的甲壳（角质盾片+骨板，与脊椎和肋骨融合）增加负重；短肢低代谢率适应防御策略而非逃跑策略。龟类寿命与低代谢率、高效DNA修复机制和端粒保护相关。加拉帕戈斯象龟平均寿命超100年，已知最长寿个体(Jonathan)超190岁。",
    "experiment": {
      "name": "快和慢的比赛",
      "steps": [
        "在地上画一条跑道",
        "让宝宝快速跑到终点，计时",
        "再让宝宝像乌龟一样慢慢爬到终点，比比时间"
      ],
      "sayToChild": "跑得快很厉害，但乌龟慢慢来也有它的好处——它不需要跑，缩进壳里就安全了，而且慢慢生活让它能活一百多岁呢！每种方式都有自己的好处。",
      "materials": [
        "粉笔或胶带（画跑道用）"
      ],
      "duration": "约5分钟",
      "safetyNote": "请在大人陪伴下进行",
      "experimentType": "hands-on",
      "image": "images/animals/animals-030-experiment.webp"
    },
    "ipScene": "问问兔和乌龟比赛跑步赢了，得意地笑。答答熊说：“乌龟不需要跑得快，它有壳保护自己。而且乌龟能活一百多岁呢，慢慢来也很厉害！”",
    "scienceImage": "images/animals/animals-030-science.webp",
    "warmClosing": "乌龟虽然慢，但它能活一百多岁呢，慢慢来也是一种本领！",
    "locale": "zh-CN"
  },
  {
    "id": "animals-031",
    "category": "animals",
    "question": "为什么树木能长那么高？",
    "age": "4-6岁",
    "tags": [
      "树木",
      "植物",
      "生长"
    ],
    "safetyLevel": "A",
    "layer1": {
      "answer": "树木从小树苗开始，年年长高长粗，有的能长到几十层楼那么高！",
      "image": "images/animals/animals-031-layer1.webp"
    },
    "layer2": {
      "followUp": "树木靠什么长高？",
      "answer": "树木的枝尖有一个生长的地方，不停地往上冒出新的细胞让树变高。树干每年还会在外面加一圈新的木头让自己变粗变结实，砍断树看到的年轮就是每年加的一圈。",
      "image": "images/animals/animals-031-layer2.webp"
    },
    "layer3": {
      "followUp": "树为什么不能无限长高？",
      "answer": "水要从根部一路运到树顶，越高越难。世界上最高的树是美国的一棵红杉，高一百一十六米。再高的话水运不到顶，叶子就会干枯。树也有自己的极限，但一百多米已经很了不起了，相当于三十多层楼！",
      "image": "images/animals/animals-031-layer3.webp"
    },
    "science": "树木高度生长依赖茎尖分生组织细胞分裂。水分运输通过导管/管胞中的蒸腾-内聚-张力机制（水分子氢键形成连续水柱，叶面蒸腾产生负压向上拉动），理论极限约130m（受水的空穴化限制）。最高树种为海岸红杉（Sequoia sempervirens），已知最高个体Hyperion为116.07m。年轮由形成层每年向外产生的次生木质部形成。",
    "experiment": {
      "name": "大树年轮观察",
      "steps": [
        "找一段被锯断的树干或树枝截面",
        "数一数上面有多少圈年轮",
        "告诉宝宝每一圈代表一年的成长"
      ],
      "sayToChild": "每一圈年轮就是树长大了一岁！你数数有几圈就知道这棵树活了几岁。树每年都在外面加一圈新木头让自己更结实更高。",
      "materials": [
        "树干截面或树桩照片",
        "放大镜（可选）"
      ],
      "duration": "约5分钟",
      "safetyNote": "请在大人陪伴下进行",
      "experimentType": "observation",
      "image": "images/animals/animals-031-experiment.webp"
    },
    "ipScene": "问问兔仰头看一棵大树说：“这棵树比房子还高！“答答熊抱住树干说：“它每年都在长，这些年轮说明它已经长了好多好多年了！”",
    "scienceImage": "images/animals/animals-031-science.webp",
    "warmClosing": "一棵大树每年都在悄悄长高，就像你一样在慢慢长大呢！",
    "locale": "zh-CN"
  },
  {
    "id": "animals-032",
    "category": "animals",
    "question": "为什么有的动物冬天要冬眠？",
    "age": "3-5岁",
    "tags": [
      "冬眠",
      "动物",
      "冬天"
    ],
    "safetyLevel": "A",
    "layer1": {
      "answer": "冬天太冷食物太少，有的动物就睡一个大大的长觉等春天来。",
      "image": "images/animals/animals-032-layer1.webp"
    },
    "layer2": {
      "followUp": "冬眠的时候动物在干什么？",
      "answer": "冬眠时动物的心跳变得很慢很慢，呼吸也很慢，体温降低，几乎不消耗能量。靠秋天储存在身体里的脂肪慢慢消耗过冬。就像手机开了省电模式一样。",
      "image": "images/animals/animals-032-layer2.webp"
    },
    "layer3": {
      "followUp": "哪些动物会冬眠？",
      "answer": "刺猬、蝙蝠、旱獭和一些蛇、青蛙都会冬眠。熊其实不是真正的冬眠，它只是浅睡，体温降得不多，被吵醒还会起来。真正冬眠的动物体温能降到接近零度，几个月不吃不喝。",
      "image": "images/animals/animals-032-layer3.webp"
    },
    "science": "冬眠（hibernation）是恒温动物的生理适应策略：体温可降至接近环境温度（某些地松鼠低至-2.9°C），心率从每分钟数百次降至个位数，代谢率降至正常的1-5%。能量来源为秋季储存的棕色脂肪组织（BAT）。熊的冬季休眠（torpor）不同于真冬眠：体温仅降5-8°C，可较快唤醒。",
    "experiment": {
      "name": "冬眠模拟",
      "steps": [
        "让宝宝先在房间里跑几圈，摸摸自己的手——热热的，心跳快快的",
        "然后安静地坐下来闭眼休息两分钟",
        "再摸摸手——没那么热了，心跳也慢了"
      ],
      "sayToChild": "你安静下来心跳变慢了、身体也没那么热了。冬眠的动物就是把身体调到最最安静的模式，心跳慢到几乎感觉不到，靠身上的脂肪慢慢过冬。",
      "materials": [
        "无需特殊材料"
      ],
      "duration": "约5分钟",
      "safetyNote": "请在大人陪伴下进行",
      "experimentType": "hands-on",
      "image": "images/animals/animals-032-experiment.webp"
    },
    "ipScene": "问问兔看到刺猬缩成一团不动说：“它怎么了？“答答熊小声说：“嘘，它在冬眠呢。天冷没东西吃，它就睡一个大长觉等春天来。”",
    "scienceImage": "images/animals/animals-032-science.webp",
    "warmClosing": "冬眠的动物在等春天，就像种子在土里等着发芽一样！",
    "locale": "zh-CN"
  },
  {
    "id": "animals-033",
    "category": "animals",
    "question": "为什么鲸鱼会喷水？",
    "age": "2-4岁",
    "tags": [
      "鲸鱼",
      "海洋",
      "呼吸"
    ],
    "safetyLevel": "A",
    "layer1": {
      "answer": "鲸鱼用头顶上的小孔呼吸，浮上来呼气时把肺里的热气喷出来，碰到冷空气就变成水雾了！",
      "image": "images/animals/animals-033-layer1.webp"
    },
    "layer2": {
      "followUp": "鲸鱼不是鱼吗？",
      "answer": "鲸鱼虽然叫“鱼“但不是鱼，它是哺乳动物，和我们一样用肺呼吸。它必须浮到水面换气，不能一直待在水下。鲸鱼宝宝也是喝奶长大的。",
      "image": "images/animals/animals-033-layer2.webp"
    },
    "layer3": {
      "followUp": "鲸鱼能在水里憋多久？",
      "answer": "不同鲸鱼憋气能力不同。蓝鲸大约能在水下待三十分钟。抹香鲸最厉害，能潜到两千多米深，憋气超过一个小时！它们的肌肉里有特殊的储氧蛋白质，就像自带氧气瓶一样。",
      "image": "images/animals/animals-033-layer3.webp"
    },
    "science": "鲸类通过头顶的喷气孔（blowhole，鼻孔演化而来）呼吸。呼气时肺内湿热空气（约37°C，水蒸气饱和）遇冷凝结成可见水雾。鲸类具有高浓度肌红蛋白（myoglobin）储存O₂，可收缩外周血管减少非重要器官供血。抹香鲸可潜至2250m，闭气超90分钟。蓝鲸一次呼吸可交换约80-90%肺容量（人类仅约10-15%）。",
    "experiment": {
      "name": "呼气变雾实验",
      "steps": [
        "在冬天的冷空气里，让宝宝用力呼一口气",
        "看到白色的“雾气“了——这就和鲸鱼喷水一样",
        "告诉宝宝鲸鱼头上有个小孔，呼气时热气碰到冷空气就变成了水雾柱"
      ],
      "sayToChild": "你看，你呼出的热气碰到冷空气就变成白雾了！鲸鱼喷水也是一样的道理，它用头顶的小孔呼气，热气碰到冷海风就变成高高的水雾柱。",
      "materials": [
        "无需特殊材料"
      ],
      "duration": "约3分钟",
      "safetyNote": "请在大人陪伴下进行",
      "experimentType": "hands-on",
      "image": "images/animals/animals-033-experiment.webp"
    },
    "ipScene": "问问兔看到鲸鱼喷出高高的水柱惊呼：“它在喷泉吗？“答答熊说：“那是鲸鱼在呼气呢！鲸鱼虽然住在水里，但和你一样用肺呼吸，要经常浮上来换气。”",
    "scienceImage": "images/animals/animals-033-science.webp",
    "warmClosing": "鲸鱼虽然住在水里却要浮上来呼吸，它是海洋里最大的哺乳动物呢！",
    "locale": "zh-CN"
  },
  {
    "id": "animals-034",
    "category": "animals",
    "question": "为什么孔雀会开屏？",
    "age": "2-6岁",
    "tags": [
      "动物",
      "孔雀",
      "求偶"
    ],
    "safetyLevel": "A",
    "layer1": {
      "answer": "孔雀开屏是在“臭美”给母孔雀看！就像小朋友穿上漂亮衣服转圈给大家看一样。",
      "image": "images/animals/animals-034-layer1.webp"
    },
    "layer2": {
      "followUp": "为什么只有公孔雀才开屏？",
      "answer": "在孔雀家族里，公孔雀负责“打扮”自己来吸引母孔雀。尾巴上的彩色大眼斑越多越亮，母孔雀就觉得它越健康越厉害，愿意和它组建家庭。母孔雀不需要漂亮尾巴，她负责孵蛋带宝宝，灰扑扑的颜色反而能躲在草丛里保护小宝宝。",
      "image": "images/animals/animals-034-layer2.webp"
    },
    "layer3": {
      "followUp": "孔雀的尾巴那么大不会累吗？",
      "answer": "公孔雀的尾屏可以有150多根羽毛，展开像一把大扇子。虽然很重，但为了找到老婆值得！不过孔雀不只是求偶才开屏——遇到危险时也会突然展开尾巴，上面的大眼斑看起来像很多眼睛在盯着敌人，能把天敌吓一跳。科学家还发现，尾羽抖动时会发出人耳听不到的次声波，远处的母孔雀也能“感觉到”！",
      "image": "images/animals/animals-034-layer3.webp"
    },
    "science": "雄性蓝孔雀（Pavo cristatus）的尾上覆羽（非真正尾羽）可达150根以上，含有由黑色素和光子晶体结构产生的虹彩色。开屏行为主要由雄性激素（睾酮）驱动，属于性选择（sexual selection）范畴。研究表明尾屏眼斑数量和对称性与雄性健康状况和遗传质量正相关（Hamilton-Zuk假说）。尾羽抖动频率约26Hz，可产生次声波（infrasound），雌孔雀头部冠羽可能起到感应作用。",
    "experiment": {
      "name": "孔雀开屏扇子实验",
      "steps": [
        "用彩色卡纸剪出一个大扇形，画上很多圆形的‘眼斑’花纹",
        "把扇子折叠收起来，然后突然展开——像不像孔雀开屏？",
        "试试快速抖动展开的扇子，感受气流——孔雀就是这样发出‘看不见的信号’的"
      ],
      "sayToChild": "你看，我们做了一把孔雀尾巴！展开的时候是不是特别漂亮？孔雀就是用这么漂亮的尾巴来吸引朋友的，抖动的时候还能发出我们听不到的声音呢！",
      "materials": [
        "彩色卡纸",
        "彩笔",
        "剪刀",
        "胶棒"
      ],
      "duration": "约10分钟",
      "safetyNote": "剪刀请在大人帮助下使用",
      "experimentType": "hands-on",
      "image": "images/animals/animals-034-experiment.webp"
    },
    "ipScene": "动物园里，问问兔看到公孔雀突然展开巨大的彩色尾巴，惊呆了：“哇！它变成一把超级大扇子了！”答答熊笑着说：“它在向母孔雀展示自己有多帅呢！你看那些像眼睛一样的花纹，越多越亮就说明它越健康。这可是孔雀家族的‘选美比赛’！”",
    "scienceImage": "images/animals/animals-034-science.webp",
    "warmClosing": "孔雀用最美丽的方式表达自己，大自然里每种动物都有独特的‘说话’方式呢！",
    "locale": "zh-CN"
  },
  {
    "id": "animals-035",
    "category": "animals",
    "question": "为什么有的虫子从高处掉下来不会摔伤？",
    "age": "2-6岁",
    "tags": [
      "昆虫",
      "物理",
      "体型"
    ],
    "safetyLevel": "A",
    "layer1": {
      "answer": "因为虫子太轻太小了，掉下来就像一片小树叶飘下来一样，根本摔不疼！",
      "image": "images/animals/animals-035-layer1.webp"
    },
    "layer2": {
      "followUp": "为什么轻就摔不疼呢？",
      "answer": "东西越小越轻，掉下来受到的空气阻力就越容易把它“刹住”。小蚂蚁从桌子上掉下来，空气就像一个软软的大垫子接住了它。但是大象如果从同样高度掉下来，它太重了空气“垫子”根本接不住，就会摔得很重。",
      "image": "images/animals/animals-035-layer2.webp"
    },
    "layer3": {
      "followUp": "那从多高掉下来虫子都不会受伤吗？",
      "answer": "大部分小虫子就算从飞机上掉下来也不会摔死！这是因为它们的体重和身体面积的比例很特别——科学家叫它“平方-立方定律”。身体缩小时重量减少得比表面积快得多，所以小虫子相对于体重来说“降落伞”特别大。而且虫子的身体外面有硬壳保护，就像穿着盔甲一样！",
      "image": "images/animals/animals-035-layer3.webp"
    },
    "science": "这涉及平方-立方定律（square-cube law）：体型缩小时，质量按长度三次方减少，而表面积按二次方减少，使得小型生物的面积/质量比极高。昆虫终端速度（terminal velocity）很低（如蚂蚁约3.9 km/h），远低于造成损伤的阈值。加之昆虫外骨骼（几丁质）具有优异的抗冲击性能，且体内无骨骼和大型器官惯性损伤风险，因此小型昆虫从任意高度坠落几乎不会受伤。",
    "experiment": {
      "name": "大小降落对比实验",
      "steps": [
        "准备一张大纸和一个小纸团（揉紧），同时从相同高度放手",
        "观察：大纸飘飘悠悠慢慢落下，小纸团‘啪’地掉下去",
        "再把大纸也揉成跟小纸团一样大的团——它是不是也掉得快了？这就说明面积大的东西空气能托住它"
      ],
      "sayToChild": "你看，大纸片像虫子一样轻飘飘地飘下来，因为空气像大垫子一样托着它。揉成团以后就掉得快了——虫子这么小这么轻，空气随时都能接住它！",
      "materials": [
        "A4纸两张"
      ],
      "duration": "约3分钟",
      "safetyNote": "请在大人陪伴下进行",
      "experimentType": "hands-on",
      "image": "images/animals/animals-035-experiment.webp"
    },
    "ipScene": "问问兔看到一只小瓢虫从树顶掉了下来，吓得赶紧伸手去接：“小心！”结果小瓢虫稳稳地落在地上，拍拍翅膀若无其事地走了。答答熊解释说：“别担心！小虫子太轻了，空气就像一个大大的棉花糖垫子，稳稳地接住它。就算从更高的地方掉下来也没事！”",
    "scienceImage": "images/animals/animals-035-science.webp",
    "warmClosing": "小小的虫子有大大的本领，大自然给了每种生物适合自己体型的保护方式！",
    "locale": "zh-CN"
  },
  {
    "id": "animals-036",
    "category": "animals",
    "question": "为什么猫咪老用爪子洗脸？",
    "age": "2-6岁",
    "tags": [
      "动物",
      "猫",
      "清洁"
    ],
    "safetyLevel": "A",
    "layer1": {
      "answer": "猫咪的脸够不到舌头舔，就用爪子蘸上口水来擦脸，就像我们用毛巾洗脸一样！",
      "image": "images/animals/animals-036-layer1.webp"
    },
    "layer2": {
      "followUp": "猫咪为什么这么爱干净？",
      "answer": "猫咪是天生的“小洁癖”！它们用带小刺的舌头舔毛就像用梳子梳头。洗脸不只是爱干净——脸上有很多重要的感应器官（胡子、眼睛、鼻子），保持干净才能灵敏。而且猫吃完东西后要把嘴边的味道擦掉，免得被猎物闻到它来了！",
      "image": "images/animals/animals-036-layer2.webp"
    },
    "layer3": {
      "followUp": "猫咪还有什么特别的清洁习惯？",
      "answer": "猫咪每天要花三四个小时舔毛洗澡！它的舌头上有很多朝后弯的小刺（叫丝状乳突），像一把随身携带的梳子。舔毛不仅能去除脏东西和寄生虫，还能把皮肤上的油脂均匀涂在毛上防水。热天多舔几下口水蒸发还能散热。猫咪之间互相舔毛还表示“我喜欢你”——这叫社交梳理！",
      "image": "images/animals/animals-036-layer3.webp"
    },
    "science": "猫舌面覆盖约300个丝状乳突（filiform papillae），由角蛋白构成，中空勺状结构可携带唾液深入毛层。猫每天花约24-50%清醒时间进行梳理行为（grooming）。面部梳理采用“前爪转移法”——先舔湿前爪再擦拭脸部，因舌头物理上无法直接到达面部区域。清洁功能包括：去除寄生虫和碎屑、分布皮脂（防水保温）、蒸发散热（猫汗腺仅在足垫）、以及通过社交梳理（allogrooming）维系群体关系。",
    "experiment": {
      "name": "猫咪洗脸模仿实验",
      "steps": [
        "让宝宝试试不用手、只用舌头能不能舔到自己的脸——是不是很难？",
        "然后用湿毛巾擦脸——这就是猫咪用爪子洗脸的方式，先沾湿再擦",
        "再摸摸魔术贴粗的那面——猫咪舌头上的小刺就是这种感觉，能梳毛去脏东西"
      ],
      "sayToChild": "你看，你用舌头够不到脸对不对？猫咪也一样！所以它先把爪子舔湿当‘毛巾’，再擦脸。猫咪的舌头上还有像小刷子一样的刺，舔毛就像在梳头！",
      "materials": [
        "湿毛巾",
        "魔术贴（可选）"
      ],
      "duration": "约3分钟",
      "safetyNote": "请在大人陪伴下进行",
      "experimentType": "hands-on",
      "image": "images/animals/animals-036-experiment.webp"
    },
    "ipScene": "问问兔看到邻居家的猫咪坐在窗台上用爪子一下一下擦脸，好奇地问：“猫咪在干嘛？它爪子上有肥皂吗？”答答熊笑着说：“猫咪在洗脸呢！它先把爪子舔湿当毛巾，再擦擦脸。猫咪可是爱干净的小达人，每天要花好几个小时给自己洗澡呢！”",
    "scienceImage": "images/animals/animals-036-science.webp",
    "warmClosing": "猫咪用自己的方式保持干净，每种小动物都有属于自己的生活智慧呢！",
    "locale": "zh-CN"
  },
  {
    "id": "animals-037",
    "category": "animals",
    "question": "为什么树桩上有一圈一圈的花纹？",
    "age": "2-6岁",
    "tags": [
      "植物",
      "年轮",
      "生长"
    ],
    "safetyLevel": "A",
    "layer1": {
      "answer": "那是大树的“年轮”，树每长一岁就多一圈，数一数就知道大树几岁了！",
      "image": "images/animals/animals-037-layer1.webp"
    },
    "layer2": {
      "followUp": "为什么会一圈一圈的？",
      "answer": "春天和夏天雨水多阳光好，大树长得快，新长的木头颜色浅、比较松软。秋天和冬天天冷了长得慢，木头颜色深、特别紧密。一浅一深就变成了一圈。每过一年就加一圈，就像大树在给自己画生日蛋糕上的蜡烛一样！",
      "image": "images/animals/animals-037-layer2.webp"
    },
    "layer3": {
      "followUp": "从年轮还能看出什么？",
      "answer": "年轮像大树的“日记本”！如果某一年圈特别宽，说明那年雨水多、阳光好，大树长得开心。如果圈很窄，可能那年干旱或者太冷。如果年轮不是正圆而是一边宽一边窄，说明那边有更多阳光或者树被风吹得倾斜了。科学家还能通过几千年的古树年轮知道古代的气候呢！",
      "image": "images/animals/animals-037-layer3.webp"
    },
    "science": "年轮（growth ring）由维管形成层季节性生长速率差异产生。春材（earlywood）细胞大壁薄，色浅；秋材（latewood）细胞小壁厚，色深。一个生长季形成一个年轮。年轮学（dendrochronology）可推断树龄、历史气候（年轮宽度与降水/温度正相关）、火灾记录（火疤）等。偏心年轮（反应木/应力木）反映力学环境。热带常绿树种因缺乏明显季节变化可能无清晰年轮。",
    "experiment": {
      "name": "年轮日记实验",
      "steps": [
        "找一片树桩或一段木头横截面（公园里常有），数一数有多少圈年轮",
        "看看哪些圈宽哪些圈窄——宽的那年大树长得好，窄的那年可能缺水",
        "用彩笔在纸上画自己的‘年轮’——今年几岁就画几圈，开心的年份画宽一点"
      ],
      "sayToChild": "你看，数一圈就是一岁！这棵树有这么多圈，比你大好多呢。宽的圈说明那年过得好，窄的圈可能那年缺水。我们也来画你的年轮日记吧！",
      "materials": [
        "树桩或木头横截面（观察用）",
        "纸",
        "彩笔"
      ],
      "duration": "约10分钟",
      "safetyNote": "请在大人陪伴下进行",
      "experimentType": "hands-on",
      "image": "images/animals/animals-037-experiment.webp"
    },
    "ipScene": "问问兔蹲在一个大树桩前数圈圈：“一、二、三……好多好多圈！这是谁画上去的？”答答熊弯下腰说：“这是大树自己画的‘生日蛋糕’！每过一年就多一圈。你数数有多少圈，就知道这棵大树活了多少年。看这里宽宽的圈，说明那年阳光雨水都很好，大树长得特别开心！”",
    "scienceImage": "images/animals/animals-037-science.webp",
    "warmClosing": "每棵大树都在用年轮记录自己的故事，大自然的日记本可真是太神奇了！",
    "locale": "zh-CN"
  },
  {
    "id": "animals-038",
    "category": "animals",
    "question": "为什么企鹅不怕冷？",
    "age": "2-6岁",
    "tags": [
      "动物",
      "企鹅",
      "保暖"
    ],
    "safetyLevel": "A",
    "layer1": {
      "answer": "企鹅穿着厚厚的“羽绒服”，还有一层油油的脂肪当“保暖内衣”，所以一点都不冷！",
      "image": "images/animals/animals-038-layer1.webp"
    },
    "layer2": {
      "followUp": "企鹅的‘羽绒服’有什么特别的？",
      "answer": "企鹅的羽毛跟其他鸟很不一样——它的羽毛又短又密，像鱼鳞一样一片叠一片排列得紧紧的，风和水都钻不进去。每平方厘米有100根羽毛，比你头发还密！靠近皮肤的绒毛层能锁住温暖的空气，就像我们穿羽绒服里面的蓬松鹅绒一样。",
      "image": "images/animals/animals-038-layer2.webp"
    },
    "layer3": {
      "followUp": "企鹅的脚踩在冰上不冻吗？",
      "answer": "企鹅脚里有一个超聪明的设计叫“逆流热交换”！去脚的动脉血管和回来的静脉血管紧紧挨在一起，热血先把温度传给回来的冷血再到脚上，这样脚只维持在刚好不结冰的温度（大约0-2°C），既不会冻伤也不会浪费热量。帝企鹅还会大家挤在一起轮流站外圈挡风，“企鹅暖气团”中心温度能超过35°C呢！",
      "image": "images/animals/animals-038-layer3.webp"
    },
    "science": "企鹅的御寒机制包括：①羽毛密度极高（约100根/cm²），外层防水防风，内层绒羽锁住隔热空气层。②皮下脂肪层厚达2-3cm（帝企鹅），提供隔热和能量储备。③足部逆流热交换系统（countercurrent heat exchange）：动静脉紧密交织，将动脉血热量预先传递给返回的静脉血，使足部维持在约0-2°C，最小化热损失。④帝企鹅（Aptenodytes forsteri）的群体聚集行为（huddling），核心温度可达37°C以上，个体轮流从边缘移向中心。",
    "experiment": {
      "name": "企鹅保暖大比拼",
      "steps": [
        "准备两杯同样温度的热水，一杯包上厚毛巾（模拟企鹅脂肪+羽毛），一杯不包",
        "半小时后摸摸两杯水——包毛巾的是不是还温热？没包的已经凉了",
        "再让全家人挤在一起和一个人单独站着比——挤在一起是不是更暖？这就是企鹅的‘暖气团’策略"
      ],
      "sayToChild": "你看，包了‘羽绒服’的杯子还是温热的！企鹅就是这样，用厚厚的羽毛和脂肪把热量锁在身体里。它们还会大家挤在一起取暖，轮流站在外面挡风，真是又聪明又团结！",
      "materials": [
        "两个杯子",
        "热水",
        "厚毛巾"
      ],
      "duration": "约30分钟（含等待时间）",
      "safetyNote": "热水请由大人倒，小心烫伤",
      "experimentType": "hands-on",
      "image": "images/animals/animals-038-experiment.webp"
    },
    "ipScene": "问问兔裹着围巾冻得发抖：“好冷好冷！企鹅住在冰天雪地里怎么不冷啊？”答答熊拍拍圆滚滚的肚子说：“企鹅有三件宝贝：密密麻麻的防风羽毛、厚厚的脂肪‘保暖内衣’，还有大家挤在一起的‘企鹅暖气团’！它们的脚还有特殊的血管设计，踩在冰上也不会冻伤呢。”",
    "scienceImage": "images/animals/animals-038-science.webp",
    "warmClosing": "企鹅用智慧和团结打败了严寒，在最冷的地方也能快乐地生活！",
    "locale": "zh-CN"
  },
  {
    "id": "animals-039",
    "category": "animals",
    "question": "为什么苍蝇总是搓手？",
    "age": "2-6岁",
    "tags": [
      "昆虫",
      "苍蝇",
      "清洁"
    ],
    "safetyLevel": "A",
    "layer1": {
      "answer": "苍蝇在“洗手”呢！它的手（前脚）上有很多感应器，搓干净了才能尝出食物的味道！",
      "image": "images/animals/animals-039-layer1.webp"
    },
    "layer2": {
      "followUp": "苍蝇的手能尝味道？",
      "answer": "苍蝇的脚上有很多微小的味觉感应毛，相当于我们的舌头长在了脚上！它落在食物上，脚一踩就能“尝”到甜不甜、能不能吃。如果脚上沾了脏东西把感应器堵住了就尝不到了，所以它要不停搓脚来清理，就像我们吃饭前要洗手一样。",
      "image": "images/animals/animals-039-layer2.webp"
    },
    "layer3": {
      "followUp": "苍蝇的脚上还有什么特别的？",
      "answer": "苍蝇脚底有两个小垫子（叫爪垫），上面会分泌一层薄薄的黏液，让它能倒着走在天花板上都不掉下来——就像穿了吸盘鞋。但黏液也容易粘上灰尘和脏东西，所以更需要经常搓脚清理。苍蝇还会搓头和搓翅膀，清理复眼和飞行翼面上的灰尘。它虽然看起来脏脏的，但其实是非常爱‘洗澡’的昆虫！",
      "image": "images/animals/animals-039-layer3.webp"
    },
    "science": "家蝇（Musca domestica）的跗节末端具有化学感受器（chemoreceptor），可检测糖类和其他化合物。爪垫（pulvilli）分泌含三酰甘油和碳氢化合物的黏液，实现在光滑表面的附着（van der Waals力辅助）。搓足行为（grooming）清除感受器和爪垫上积累的颗粒物和微生物，维持味觉灵敏度和附着力。研究表明被阻止梳理的苍蝇飞行和觅食能力显著下降。苍蝇全身梳理顺序具有固定优先级：头部 > 前足 > 后足 > 翅膀 > 腹部。",
    "experiment": {
      "name": "手指味觉实验",
      "steps": [
        "让宝宝闭上眼，把手指贴在一小片苹果上——能猜出是什么吗？（只靠触觉很难）",
        "再用舌头尝一下——马上就知道是苹果了！苍蝇的脚就像我们的舌头",
        "往手指上抹一点面粉再去摸苹果——触感变模糊了吧？苍蝇搓手就是为了去掉这些‘面粉’"
      ],
      "sayToChild": "你看，手指上沾了东西就摸不清楚了对不对？苍蝇的脚比你的舌头还灵敏，可以尝出食物的味道。所以它要经常搓搓手把脏东西去掉，这样才能找到好吃的！",
      "materials": [
        "苹果或其他水果一小块",
        "少量面粉"
      ],
      "duration": "约5分钟",
      "safetyNote": "注意食品卫生，请在大人陪伴下进行",
      "experimentType": "hands-on",
      "image": "images/animals/animals-039-experiment.webp"
    },
    "ipScene": "问问兔看见苍蝇落在桌上不停搓前脚，好奇地歪头看：“它怎么一直搓手？是在打什么坏主意吗？”答答熊哈哈大笑：“它在‘洗手’呢！苍蝇的脚上长着像舌头一样的味觉感应器，搓搓手把脏东西清掉才能尝出食物味道。你看，苍蝇也知道饭前要‘洗手’！”",
    "scienceImage": "images/animals/animals-039-science.webp",
    "warmClosing": "小小的苍蝇也有大大的生存智慧，仔细观察就能发现每种生物都在用自己的方式生活！",
    "locale": "zh-CN"
  },
  {
    "id": "animals-040",
    "category": "animals",
    "question": "为什么有些植物能爬墙爬上好高？",
    "age": "2-6岁",
    "tags": [
      "植物",
      "攀爬",
      "适应"
    ],
    "safetyLevel": "A",
    "layer1": {
      "answer": "爬墙的植物有“小手”或“小吸盘”，能抓住墙壁一点一点往上爬去找阳光！",
      "image": "images/animals/animals-040-layer1.webp"
    },
    "layer2": {
      "followUp": "植物的小手长什么样？",
      "answer": "不同的植物有不同的“爬墙工具”！爬山虎脚上长着小吸盘，能牢牢吸住墙面。牵牛花用细细的卷须像弹簧一样缠绕着架子往上绕。常春藤从茎上长出气根，像小钩子一样扎进墙缝里。它们虽然没有脚不能走路，但都有自己爬高的小妙招！",
      "image": "images/animals/animals-040-layer2.webp"
    },
    "layer3": {
      "followUp": "它们为什么要费力气爬那么高呢？",
      "answer": "因为地面上太挤了，大树的影子遮住了阳光，矮小的植物晒不到太阳就做不了“饭”（光合作用）。所以有些植物学会了不自己长粗壮的树干，而是借别人的墙壁和树干往上爬——这样用很少的力气就能爬到高处晒太阳。这就像坐电梯比爬楼梯省力一样！",
      "image": "images/animals/animals-040-layer3.webp"
    },
    "science": "攀缘植物的攀附方式主要有：①吸盘型（如爬山虎，卷须末端分泌黏性物质形成吸附垫）；②卷须缠绕型（如葡萄、黄瓜，触碰刺激引起不等速生长形成螺旋）；③气生根型（如常春藤、薜荔，茎节处生出不定根插入基质裂隙）；④茎缠绕型（如牵牛花，顶端做环形回旋运动）。这些策略让植物以最低的结构投入（无需粗大木质茎）获得竞争性光照资源。",
    "experiment": {
      "name": "植物攀爬观察实验",
      "steps": [
        "种一株牵牛花或豌豆，在花盆旁边插一根筷子或拉一根绳子",
        "每天观察嫩茎顶端是怎样转圈寻找“抓手”的",
        "找到支撑物后它会自动缠上去！也可以观察小区围墙上的爬山虎，轻轻翻开一片叶子看看下面的小吸盘"
      ],
      "sayToChild": "你看，牵牛花的小藤蔓在转圈圈找东西抓呢！它一找到筷子就会缠上去。爬山虎更厉害，叶子下面有小吸盘直接吸在墙上。植物虽然不能走，但能想办法爬高晒太阳！",
      "materials": [
        "牵牛花或豌豆种子",
        "花盆",
        "筷子或细绳"
      ],
      "duration": "每天观察几分钟，持续1-2周",
      "safetyNote": "请在大人陪伴下进行",
      "experimentType": "observation",
      "image": "images/animals/animals-040-experiment.webp"
    },
    "ipScene": "问问兔仰着头看一面绿绿的墙：“这面墙怎么长满了叶子？植物怎么爬上去的？”答答熊轻轻翻起一片爬山虎的叶子，露出下面的小吸盘：“看！每片叶子下面都有小吸盘在抓着墙呢。它们想晒太阳，就一步一步吸着墙往上爬，比你爬楼梯还厉害！”",
    "scienceImage": "images/animals/animals-040-science.webp",
    "warmClosing": "植物虽然不能走路，但用聪明的方式找到阳光，大自然的智慧真了不起！",
    "locale": "zh-CN"
  },
  {
    "id": "animals-041",
    "category": "animals",
    "question": "为什么兔子的耳朵那么大？",
    "age": "2-6岁",
    "tags": [
      "动物",
      "兔子",
      "听觉"
    ],
    "safetyLevel": "A",
    "layer1": {
      "answer": "兔子的大耳朵像两个“声音雷达”，能转来转去收集声音，早早听到危险！",
      "image": "images/animals/animals-041-layer1.webp"
    },
    "layer2": {
      "followUp": "为什么兔子需要那么灵的耳朵？",
      "answer": "兔子是很多动物的“小点心”——狐狸、老鹰、蛇都想吃它。兔子跑得快，但得先知道危险从哪里来呀！大耳朵能接收到很远很轻的声音，而且两只耳朵可以分别转向不同方向，像两个独立的小天线一样，能判断声音从哪边来的，赶紧往反方向跑！",
      "image": "images/animals/animals-041-layer2.webp"
    },
    "layer3": {
      "followUp": "大耳朵还有别的用处吗？",
      "answer": "兔子的大耳朵还是“空调”！兔子不会出汗，热的时候耳朵里的血管会膨胀，让热乎乎的血液流过薄薄的耳朵皮肤，把热量散到空气中。所以住在沙漠里的兔子耳朵特别特别大（比如长耳大野兔），住在寒冷地方的兔子耳朵就比较短——因为太大的耳朵在冬天反而会把热量散掉！",
      "image": "images/animals/animals-041-layer3.webp"
    },
    "science": "兔耳具有双重功能：①听觉——耳廓面积大增加了声波收集效率，每只耳可独立旋转270°，实现双耳定位（binaural localization），探测频率范围360Hz-42kHz。②体温调节——耳部动静脉吻合支丰富，炎热时血管舒张散热（可散发全身热量的33%），寒冷时血管收缩减少热损失。这解释了Allen法则中不同气候兔种耳廓大小的差异。",
    "experiment": {
      "name": "纸耳朵听声实验",
      "steps": [
        "用两张A4纸卷成喇叭形放在耳朵边",
        "请家人在不同方向小声说话，看是不是比平时听得更清楚了",
        "试试把‘纸耳朵’对着不同方向转——这就是兔子转耳朵的感觉"
      ],
      "sayToChild": "你听！用了纸喇叭耳朵是不是听得更清楚了？兔子的大耳朵就是这样的，还能像雷达一样转来转去找声音的方向。大耳朵不光能听声音，热天还能散热当空调呢！",
      "materials": [
        "A4纸2张",
        "胶带"
      ],
      "duration": "约5分钟",
      "safetyNote": "请在大人陪伴下进行",
      "experimentType": "hands-on",
      "image": "images/animals/animals-041-experiment.webp"
    },
    "ipScene": "问问兔骄傲地竖起自己的大耳朵说：“我能听到好远好远的声音哦！”答答熊在远处轻轻拍了一下手，问问兔立马转过耳朵指着那个方向：“是那边！”答答熊竖起大拇指：“没错！你的大耳朵就像两个小雷达，又能听声又能散热，是兔子家族最厉害的宝贝！”",
    "scienceImage": "images/animals/animals-041-science.webp",
    "warmClosing": "兔子的大耳朵是大自然送给它们的超级礼物，听声音、散热样样行！",
    "locale": "zh-CN"
  },
  {
    "id": "animals-042",
    "category": "animals",
    "question": "为什么蜗牛爬过的地方有一条亮亮的线？",
    "age": "2-6岁",
    "tags": [
      "动物",
      "蜗牛",
      "黏液"
    ],
    "safetyLevel": "A",
    "layer1": {
      "answer": "那是蜗牛的“滑滑梯胶水”！蜗牛肚子下面会分泌黏黏的液体，帮它滑着走路！",
      "image": "images/animals/animals-042-layer1.webp"
    },
    "layer2": {
      "followUp": "为什么蜗牛需要黏液才能走？",
      "answer": "蜗牛没有脚，它是用肚子下面的一整块“肌肉脚”来移动的。如果地面干干的，它的肉就会跟地面摩擦很痛。黏液就像给地板打了蜡一样，让蜗牛能顺滑地向前“滑行”。而且这个黏液很神奇——蜗牛用力推的时候它变得滑滑的，不动的时候又变得粘粘的，所以蜗牛能爬墙也不会滑下来！",
      "image": "images/animals/animals-042-layer2.webp"
    },
    "layer3": {
      "followUp": "那黏液还有什么别的用处？",
      "answer": "蜗牛的黏液是多功能“万能胶”！它能保护蜗牛柔软的身体不被尖石子划伤；能防止身体水分蒸发变干；粘粘的还能帮它翻越锋利的刀片都不会受伤。科学家还在研究蜗牛黏液的成分，想做出新型医用胶水来帮人们粘合伤口呢！",
      "image": "images/animals/animals-042-layer3.webp"
    },
    "science": "蜗牛足腺分泌的黏液是一种复杂的高分子水凝胶，含有糖蛋白和多糖。它具有非牛顿流体特性（剪切变稀）：受剪切力时黏度降低利于滑行，静止时恢复高黏度实现附着。黏液同时具有润滑、保湿、防御（含抗菌肽）和修复功能。其组分中的蜗牛蛋白已被应用于医用组织粘合剂的研究（如MIT开发的“蛞蝓胶”）。",
    "experiment": {
      "name": "蜗牛黏液模拟实验",
      "steps": [
        "下雨后去花园找蜗牛，观察它爬过的亮亮痕迹",
        "让蜗牛爬在手臂上，感受黏黏凉凉的感觉",
        "做对比实验：手指在干桌面上推和在抹了一点洗洁精的桌面上推，哪个更滑？蜗牛的黏液就起类似作用"
      ],
      "sayToChild": "你看，蜗牛爬过的地方亮闪闪的！那是它分泌的黏液，像给自己铺了一条滑滑的路。这个黏液可神奇了，动的时候变滑帮它前进，不动的时候变粘帮它粘在墙上不掉下来！",
      "materials": [
        "无需特殊材料，找个有蜗牛的潮湿花园即可",
        "少量洗洁精（可选，做对比实验）"
      ],
      "duration": "约10分钟",
      "safetyNote": "观察蜗牛后请洗手，请在大人陪伴下进行",
      "experimentType": "observation",
      "image": "images/animals/animals-042-experiment.webp"
    },
    "ipScene": "雨后的早晨，问问兔蹲在地上追着一条亮闪闪的线看：“谁在地上画了一条银色的路？”答答熊指着前面慢悠悠爬行的蜗牛说：“是蜗牛小画家！它走一步就铺一层滑滑的‘地毯’，既能保护肚子不受伤，又能粘住墙壁不掉下来。你看它爬得多从容！”",
    "scienceImage": "images/animals/animals-042-science.webp",
    "warmClosing": "蜗牛用神奇的黏液铺出自己的路，慢慢走也能到达想去的地方！",
    "locale": "zh-CN"
  },
  {
    "id": "animals-043",
    "category": "animals",
    "question": "为什么鸵鸟有翅膀却不会飞？",
    "age": "2-6岁",
    "tags": [
      "动物",
      "鸵鸟",
      "进化"
    ],
    "safetyLevel": "A",
    "layer1": {
      "answer": "鸵鸟太重了，翅膀太小了，就像你背个小书包想当降落伞——根本飞不起来！",
      "image": "images/animals/animals-043-layer1.webp"
    },
    "layer2": {
      "followUp": "那它为什么还有翅膀呢？",
      "answer": "鸵鸟的祖先很久很久以前是会飞的小鸟。后来它们发现在大草原上跑比飞更好用——地面上有吃不完的食物，而且跑得够快就能躲开坏人。于是一代代下来腿越来越粗壮，身体越来越重，翅膀就用不上了，慢慢变小了。",
      "image": "images/animals/animals-043-layer2.webp"
    },
    "layer3": {
      "followUp": "那鸵鸟的翅膀还有用吗？",
      "answer": "虽然飞不了，但翅膀没有完全“退休”！鸵鸟跑步转弯时会把翅膀展开保持平衡，就像你骑自行车转弯时伸手臂一样。公鸵鸟还会展开翅膀跳舞吸引母鸵鸟。大热天翅膀还能当“扇子”给蛋和小宝宝扇风。而且鸵鸟跑起来时速能到70公里，比汽车在城里开还快呢！",
      "image": "images/animals/animals-043-layer3.webp"
    },
    "science": "鸵鸟属平胸总目（Palaeognathae），约6000万年前与飞行鸟类分化。其胸骨缺少龙骨突（飞行肌附着点），飞行肌极度退化，羽毛缺乏钩状羽小枝（无法形成气动翼面），体重可达150kg，远超飞行体重上限（约12-15kg）。但后肢极其发达，股骨肌群占体重40%以上，奔跑时速可达70km/h，是现存最快的双足动物。",
    "experiment": {
      "name": "飞行体重实验",
      "steps": [
        "用纸做两种‘鸟’——一个用大纸翅膀配轻轻的身体（纸飞机），一个用小纸翅膀配重重的身体（纸翅膀上夹几个橡皮）",
        "分别从同样高度扔出去，看哪个飞得远",
        "再试试跑步转弯时张开手臂和不张开手臂，感受平衡的区别"
      ],
      "sayToChild": "你看，重的那个飞不起来直接掉了对不对？鸵鸟就是这样，身体太重翅膀太小。不过它的翅膀还能帮忙平衡呢——你试试跑步转弯时张开手臂，是不是更稳？",
      "materials": [
        "纸",
        "橡皮或小重物",
        "胶带"
      ],
      "duration": "约5分钟",
      "safetyNote": "请在大人陪伴下进行",
      "experimentType": "hands-on",
      "image": "images/animals/animals-043-experiment.webp"
    },
    "ipScene": "问问兔看到鸵鸟拍打翅膀却飞不起来，替它着急：“加油加油！使劲拍！”答答熊摇摇头笑着说：“鸵鸟可不想飞，它觉得跑步比飞更酷！你看它两条大长腿，跑起来比汽车还快呢。翅膀嘛，留着转弯时当方向盘用啦！”",
    "scienceImage": "images/animals/animals-043-science.webp",
    "warmClosing": "鸵鸟虽然不能飞，却是跑步冠军，大自然给了每种动物最适合的本领！",
    "locale": "zh-CN"
  },
  {
    "id": "animals-044",
    "category": "animals",
    "question": "为什么松鼠秋天喜欢到处藏坚果？",
    "age": "2-6岁",
    "tags": [
      "动物",
      "松鼠",
      "储食行为"
    ],
    "safetyLevel": "A",
    "layer1": {
      "answer": "松鼠是在为冬天“存零食”！冬天找不到食物，秋天赶紧到处埋坚果当储备粮！",
      "image": "images/animals/animals-044-layer1.webp"
    },
    "layer2": {
      "followUp": "松鼠怎么记得藏在哪里的？",
      "answer": "松鼠的记忆力可好了！它会记住大概的位置，还会用鼻子闻——隔着泥土也能闻到坚果的味道。不过松鼠确实会忘记一些，一只松鼠一年能藏一万颗坚果，大概有四分之一找不回来。但这些“忘掉的坚果”反而会在春天发芽长成新的树，松鼠不小心就变成了种树小能手！",
      "image": "images/animals/animals-044-layer2.webp"
    },
    "layer3": {
      "followUp": "那松鼠冬天不冬眠吗？为什么还需要存粮？",
      "answer": "大部分松鼠不冬眠，冬天也要出来活动找食物吃。它们把坚果分散藏在不同的地方（有时候几百个地点！），这样就算一些被别的动物偷吃了或被雪埋得太深找不到，还有其他地方的存货。这就像我们把鸡蛋放在不同篮子里一样聪明。科学家发现，松鼠还会按种类分开藏——橡子放一堆、松子放一堆，比我们收拾房间还有条理！",
      "image": "images/animals/animals-044-layer3.webp"
    },
    "science": "松鼠的分散贮藏（scatter hoarding）策略是一种反盗食适应。灰松鼠每年可贮藏约1万颗坚果，分布在数千个不同地点。恢复依赖空间记忆（海马体相对体积大于非贮藏物种）和嗅觉双重定位。未找回的坚果（约25-40%）成为种子传播途径，对森林更新有重要生态学意义。松鼠还表现出“假装埋藏”的欺骗行为以误导窃食者。",
    "experiment": {
      "name": "松鼠藏坚果记忆游戏",
      "steps": [
        "给孩子10颗糖果（代替坚果），让他藏在房间不同角落",
        "等1小时后去找——能找回几颗？",
        "第二天再试——还记得吗？体会松鼠要记住上万个藏食点有多不容易"
      ],
      "sayToChild": "你藏了10颗，找回来几颗？松鼠一年要藏一万颗呢！忘掉的坚果就在土里发芽长成小树苗了，松鼠不小心就当了种树的园丁！",
      "materials": [
        "糖果或小饼干10颗",
        "计时器"
      ],
      "duration": "约15分钟（不含等待时间）",
      "safetyNote": "请在大人陪伴下进行，注意食品卫生",
      "experimentType": "hands-on",
      "image": "images/animals/animals-044-experiment.webp"
    },
    "ipScene": "秋天的公园里，问问兔看见松鼠两颊鼓鼓地跑来跑去，一会儿在这棵树下刨坑埋东西，一会儿又跑到那边。问问兔数着：“一、二、三……它藏了好多！记得住吗？”答答熊笑着说：“松鼠在做冬天的‘外卖’储备呢！不过它总会忘掉一些，那些被忘记的坚果明年就长成小树苗啦——松鼠是不小心当上园丁的！”",
    "scienceImage": "images/animals/animals-044-science.webp",
    "warmClosing": "松鼠的小忘性成就了大森林，大自然就是这样奇妙地连接在一起！",
    "locale": "zh-CN"
  },
  {
    "id": "animals-045",
    "category": "animals",
    "question": "为什么有的花只在晚上才开？",
    "age": "2-6岁",
    "tags": [
      "植物",
      "花",
      "授粉"
    ],
    "safetyLevel": "A",
    "layer1": {
      "answer": "因为帮它们传花粉的小伙伴是晚上出来的，花要在朋友来的时候才开门！",
      "image": "images/animals/animals-045-layer1.webp"
    },
    "layer2": {
      "followUp": "晚上什么动物会来找花呀？",
      "answer": "夜晚有飞蛾、蝙蝠这些“夜猫子”帮花传花粉。晚上开的花通常是白色或浅色的（黑暗中更容易被看见），还会散发特别浓的香味（因为看不清就靠闻味道来找路）。就像夜市的摊子会挂灯笼、放香味一样，夜晚的花也要想办法“招呼”客人来！",
      "image": "images/animals/animals-045-layer2.webp"
    },
    "layer3": {
      "followUp": "那花怎么知道天黑了该开了？",
      "answer": "花有自己的“生物钟”！它们能感受到光线和温度的变化。白天温度高、光线强的时候花瓣的内侧细胞膨胀会合拢；晚上凉爽黑暗时外侧细胞膨胀就把花瓣撑开了。昙花就是最有名的“夜晚花”，只在晚上开几个小时就谢了——“昙花一现”这个成语就是从这来的！还有月光花、夜来香、晚香玉都是晚上开放的。",
      "image": "images/animals/animals-045-layer3.webp"
    },
    "science": "夜间开花是一种与夜行传粉者（如天蛾、蝙蝠）协同进化的适应策略。这些花通常具有：①白色/浅色花瓣（高反射率便于识别）；②强烈芳香（含大量萜类和苯甲酸酯类挥发物质）；③花筒深管状（匹配长喙传粉者）。开合机制由生物钟基因（CCA1/LHY）调控，花瓣运动依赖于背腹面细胞不对称膨压变化。夜开花策略还可减少水分蒸发和避免与日间花竞争传粉者。",
    "experiment": {
      "name": "花朵开合观察实验",
      "steps": [
        "如果家附近有夜来香或昙花，晚上去观察它们开花的过程（昙花通常晚上8-9点开始）",
        "白天观察牵牛花——它早晨开、中午就合了，跟夜花正好相反",
        "用手机延时摄影拍下花朵开合的过程，快放看会特别惊艳"
      ],
      "sayToChild": "你看，这朵花白天闭着，晚上才开！因为帮它传花粉的飞蛾和蝙蝠都是晚上出来的。花要在客人来的时候开门，还放出很浓的香味说‘快来呀快来呀’！",
      "materials": [
        "无需特殊材料，找个有夜来香或昙花的地方即可",
        "手机（可选，拍延时摄影）"
      ],
      "duration": "约15分钟",
      "safetyNote": "夜间外出请大人陪同",
      "experimentType": "observation",
      "image": "images/animals/animals-045-experiment.webp"
    },
    "ipScene": "傍晚散步时，问问兔指着一朵紧闭的白花说：“这朵花是不是生病了？太阳下山了它还不开。”答答熊悄悄说：“嘘——它是‘夜猫子花’，等月亮出来才营业呢！专门招待飞蛾和蝙蝠客人。你闻闻，它正在散发超级浓的香味打广告——‘这边走这边走，花蜜管够！’”",
    "scienceImage": "images/animals/animals-045-science.webp",
    "warmClosing": "花儿选择在最合适的时间绽放，大自然的每一个安排都有它的道理！",
    "locale": "zh-CN"
  },
  {
    "id": "animals-046",
    "category": "animals",
    "question": "为什么大雁飞的时候要排成人字形？",
    "age": "3-5岁",
    "tags": [
      "动植物, 鸟类, 群体行为, 空气动力学"
    ],
    "layer1": {
      "answer": "大雁排队飞，后面的大雁能借着前面大雁翅膀扇出的风，飞得不那么累。",
      "followUp": "那领头的大雁不累吗？",
      "image": "images/animals/animals-046-layer1.webp"
    },
    "layer2": {
      "answer": "前面大雁扇翅膀时，翅膀尖会留下一圈圈向上的小气流。后面的大雁稍微偏一点飞在这股气流上，就像坐上了向上抬的电梯，省力气。人字形能让每只大雁都借着前面的气流。",
      "followUp": "那它们怎么知道什么时候换领队呢？",
      "image": "images/animals/animals-046-layer2.webp"
    },
    "layer3": {
      "answer": "大雁排队飞是为了省力气。前面的大雁扇翅膀时，翅尖会制造一股向上的气流，叫\"翼尖涡流\"。后面的大雁只要稍微偏一点位置，飞在这股上升气流上，就能少用很多力气。人字形让每只大雁都能借到前面大雁的气流，飞得远还不累。领头的那只最累，所以大雁会轮流换班当领队。",
      "followUp": "其他动物也有这种合作的智慧吗？",
      "image": "images/animals/animals-046-layer3.webp"
    },
    "science": "大雁人字形编队飞行利用了翼尖涡流（wingtip vortex）。前鸟扇翅时翼尖产生升力诱导涡流，后鸟位于涡流上升区域可获得约20-30%的额外升力，显著降低诱导阻力（induced drag）和代谢能耗。人字形（V字形）夹角约110-130度时空气动力学收益最大，且保持视野畅通便于编队协调。领头鸟无法获益，因此长途迁徙中大雁会周期性轮换领飞位置以分担能耗。",
    "scienceImage": "images/animals/animals-046-science.webp",
    "ipScene": "问问兔抬头望着天空，一群大雁排成\"人\"字飞过，兔子的手指着领头雁；答答熊戴着飞行员小帽，一只手做扇翅膀的动作，旁边画着翅膀尖后面一圈圈上升的小箭头，后一只雁正好骑在箭头上。",
    "experiment": {
      "name": "大雁人字编队观察实验",
      "steps": [
        "春秋迁徙季节，带孩子在清晨或黄昏到公园、湖边或田野抬头看天，留意有没有大雁群飞过",
        "让孩子用手指跟着雁群在天空画一下它们的形状——是不是像'人'字或'一'字",
        "数一数领头雁后面跟着几只，看看它们是不是一只比一只稍微偏后、偏侧地排开",
        "如果暂时看不到真雁，也可以看看小区里常见的鸽子或麻雀群飞，对比一下它们有没有排队"
      ],
      "sayToChild": "你看，大雁不像小麻雀乱飞，它们排队飞呢！前面那只最累，所以它们会轮流换班当领队，就像小朋友排队轮流当小队长一样。",
      "materials": [
        "无需特殊材料，春秋季节户外观察即可",
        "可选：手机或望远镜"
      ],
      "duration": "约10分钟",
      "safetyNote": "户外观察请大人陪同，注意交通安全；不要直视强太阳光",
      "experimentType": "observation",
      "image": "images/animals/animals-046-experiment.webp"
    },
    "warmClosing": "下次看到天上大雁排队飞过，你可以告诉大人：它们在玩接力赛，轮流当领队呢！",
    "locale": "zh-CN",
    "safetyLevel": "A"
  },
  {
    "id": "animals-2071",
    "category": "animals",
    "tags": [],
    "safetyLevel": "A",
    "locale": "zh-CN",
    "question": "为什么猫从高处跳下来总能稳稳落地？",
    "age": "3-5岁",
    "layer1": {
      "answer": "猫咪的身体像弹簧一样灵活，它会用尾巴当方向盘，在空中扭来扭去，让自己四脚朝下稳稳落地。",
      "image": "images/animals/animals-2071-layer1.webp"
    },
    "layer2": {
      "answer": "猫有一种天生的本领叫\"翻正反射\"。它从高处掉下来时，会先转动头看地面，然后身体跟着扭，短短半秒内就把身体翻正。它的脊柱特别灵活，像一串可以自由转动的珠子。",
      "image": "images/animals/animals-2071-layer2.webp"
    },
    "layer3": {
      "answer": "猫的翻正反射是本能行为，不需学习。过程：内耳前庭检测身体方向→头先转正→前肢收拢→后半身扭转跟进→四肢伸展准备着陆。猫的锁骨退化、脊柱异常灵活（50\\+块椎骨），让它可以像体操运动员一样在空中翻转。",
      "image": "images/animals/animals-2071-layer3.webp"
    },
    "science": "猫翻正反射：角动量守恒下的身体分段扭转。猫先收前肢减小前半身转动惯量快速转正，再伸前肢增大惯量，利用反作用力扭转后半身。整个过程约0.3秒，从约30cm以上高度即可完成。",
    "scienceImage": "images/animals/animals-2071-science.webp",
    "experiment": {
      "name": "为什么猫从高处跳下来总能稳稳落地？·小实验",
      "steps": [
        "用一个小的毛绒玩具模拟\"猫翻转\"——让孩子从不同方向扔玩具到沙发上，看它落地时的姿势，讨论为什么猫能做到而玩具不行。"
      ],
      "materials": [
        "猫形毛绒玩具",
        "沙发"
      ],
      "image": "images/animals/animals-2071-experiment.webp",
      "sayToChild": "",
      "duration": "约5分钟",
      "safetyNote": "需家长全程陪同",
      "experimentType": "观察"
    },
    "ipScene": "问问兔在树上看到一只猫从围墙跳下来，四脚稳稳落地。\"猫是不是有弹簧脚？\"答答熊说\"猫的脊椎像一串灵活的珠子，它能在空中翻跟斗，把自己调到最安全的姿势落地！\"",
    "warmClosing": ""
  },
  {
    "id": "animals-2072",
    "category": "animals",
    "tags": [],
    "safetyLevel": "A",
    "locale": "zh-CN",
    "question": "为什么乌龟走得那么慢？",
    "age": "3-5岁",
    "layer1": {
      "answer": "因为乌龟背着大大的房子，太重了，所以走得慢。但它不需要快，遇到危险缩进壳里就好了。",
      "image": "images/animals/animals-2072-layer1.webp"
    },
    "layer2": {
      "answer": "乌龟有四条短短的腿，背上还扛着沉重的壳。它的腿不像兔子那样适合跳，也不像马那样适合跑。而且乌龟的新陈代谢很慢，身体不需要急着找食物，慢慢走就够了。",
      "image": "images/animals/animals-2072-layer2.webp"
    },
    "layer3": {
      "answer": "陆龟四肢短粗呈柱状，适合支撑沉重壳体但不适合快速移动。龟类代谢率极低，是变温动物，节省能量是生存策略。它们以植物为食，不需要捕猎，乌龟壳提供了强大防御，不需要速度来逃命。",
      "image": "images/animals/animals-2072-layer3.webp"
    },
    "science": "龟类的基础代谢率仅为同体重哺乳动物的10-20%。四肢结构（柱状短肢、趾骨短粗）牺牲速度换取负重和稳定性。龟壳占体重30%以上，但提供了无与伦比的抗捕食保护。",
    "scienceImage": "images/animals/animals-2072-science.webp",
    "experiment": {
      "name": "为什么乌龟走得那么慢？·小实验",
      "steps": [
        "让孩子背一个装满书的书包（模拟乌龟壳的重量），在房间里走一圈，感受\"背着房子走路\"有多累。"
      ],
      "materials": [
        "书包",
        "书"
      ],
      "image": "images/animals/animals-2072-experiment.webp",
      "sayToChild": "",
      "duration": "约5分钟",
      "safetyNote": "需家长全程陪同",
      "experimentType": "观察"
    },
    "ipScene": "问问兔蹲在路边看乌龟慢悠悠地爬，急得跺脚\"你快点呀！\"答答熊说\"乌龟不着急，它背着防弹衣走路，谁也伤不了它。慢是它的超能力，不是缺点。\"",
    "warmClosing": ""
  },
  {
    "id": "animals-2073",
    "category": "animals",
    "tags": [],
    "safetyLevel": "A",
    "locale": "zh-CN",
    "question": "为什么鱼在水里不会淹到？",
    "age": "3-5岁",
    "layer1": {
      "answer": "因为鱼用鳃呼吸，能把水里的空气吸出来用。就像你用鼻子吸空气，鱼用鳃吸水里的空气。",
      "image": "images/animals/animals-2073-layer1.webp"
    },
    "layer2": {
      "answer": "鱼的头部两侧有鳃，鳃里面有好多细细的血管。水从鱼嘴巴流进去，经过鳃的时候，鳃就把水里溶解的氧气\"抓\"出来送进血液里，然后把水从鳃盖排出去。",
      "image": "images/animals/animals-2073-layer2.webp"
    },
    "layer3": {
      "answer": "鱼鳃由鳃丝和鳃小片组成，表面积巨大，布满毛细血管。水流经鳃时，水中溶解氧通过扩散进入血液，CO₂则反向排出。鳃丝在水中展开，离开水后粘连塌陷，失去气体交换功能，鱼窒息而死。",
      "image": "images/animals/animals-2073-layer3.webp"
    },
    "science": "鳃的对流交换机制：水流方向与鳃毛细血管血流方向相反（逆流交换），使氧气提取效率高达80%以上（哺乳动物肺约25%）。水中溶解氧含量约5-10mg/L，远低于空气的210mg/L，鳃的高效结构是对此的适应。",
    "scienceImage": "images/animals/animals-2073-science.webp",
    "experiment": {
      "name": "为什么鱼在水里不会淹到？·小实验",
      "steps": [
        "观察鱼缸里的鱼——看它嘴巴和鳃盖一张一合交替开合，理解\"张嘴吸水→闭嘴→鳃盖打开排水\"的呼吸节奏。"
      ],
      "materials": [
        "鱼缸（或视频）"
      ],
      "image": "images/animals/animals-2073-experiment.webp",
      "sayToChild": "",
      "duration": "约5分钟",
      "safetyNote": "需家长全程陪同",
      "experimentType": "观察"
    },
    "ipScene": "问问兔看着鱼缸里的金鱼担心地问\"它一直泡在水里不会淹到吗？\"答答熊说\"鱼才不怕水呢！水是它的空气，它用鳃把水里的氧气捞出来，就像你用鼻子从空气里捞氧气一样。\"",
    "warmClosing": ""
  },
  {
    "id": "animals-2074",
    "category": "animals",
    "tags": [],
    "safetyLevel": "A",
    "locale": "zh-CN",
    "question": "为什么狗见面要互相闻屁股？",
    "age": "4-6岁",
    "layer1": {
      "answer": "狗用鼻子代替眼睛了解对方——闻一闻就知道对方是谁、吃了什么饭、开不开心。屁股是狗狗的\"名片\"。",
      "image": "images/animals/animals-2074-layer1.webp"
    },
    "layer2": {
      "answer": "狗屁股附近有特殊的腺体，会分泌一种带味道的液体，每只狗的味道都不一样。这就像狗狗的\"身份证\"，别的狗闻一下就知道\"你是谁、你是男是女、你今天心情好不好\"。",
      "image": "images/animals/animals-2074-layer2.webp"
    },
    "layer3": {
      "answer": "狗肛门两侧有肛门腺，分泌含信息素的液体，编码了狗的性别、年龄、健康状况、情绪和饮食等大量信息。狗的嗅觉灵敏度是人类的一万倍以上，通过闻屁股可以在几秒内完成信息交换。",
      "image": "images/animals/animals-2074-layer3.webp"
    },
    "science": "犬科肛门腺分泌的信息素含有挥发性脂肪酸、蛋白质和类固醇等，每只狗都有独特的化学\"指纹\"。犁鼻器（Jacobson's organ）专门处理信息素，通过嗅闻行为收集社交信息。",
    "scienceImage": "images/animals/animals-2074-science.webp",
    "experiment": {
      "name": "为什么狗见面要互相闻屁股？·小实验",
      "steps": [
        "类比简化：给几个不同颜色的杯子分别装上醋、酱油、柠檬汁，让孩子蒙眼靠闻来分辨。说明\"气味也能传递信息\"。"
      ],
      "materials": [
        "几个杯子",
        "醋",
        "酱油",
        "柠檬汁",
        "眼罩"
      ],
      "image": "images/animals/animals-2074-experiment.webp",
      "sayToChild": "",
      "duration": "约5分钟",
      "safetyNote": "需家长全程陪同",
      "experimentType": "观察"
    },
    "ipScene": "问问兔看到两只狗互相闻屁股，捂着嘴笑\"它们在干嘛？\"答答熊说\"这是狗狗的握手礼仪！它们的屁股上有味道名片，一闻就知道对方是谁、今天吃了什么，比我们交换名片还快呢。\"",
    "warmClosing": ""
  },
  {
    "id": "animals-2075",
    "category": "animals",
    "tags": [],
    "safetyLevel": "A",
    "locale": "zh-CN",
    "question": "为什么蜻蜓会点水？",
    "age": "3-5岁",
    "layer1": {
      "answer": "蜻蜓在水面上点来点去，是在把宝宝放进水里。蜻蜓宝宝要在水里才能长大。",
      "image": "images/animals/animals-2075-layer1.webp"
    },
    "layer2": {
      "answer": "蜻蜓妈妈在水面上飞，用尾巴尖轻轻点水，每次点水都在水里产下一颗卵。等卵孵化出来，蜻蜓宝宝就在水里生活，吃水里的蚊子幼虫，长大了再爬出来变成会飞的蜻蜓。",
      "image": "images/animals/animals-2075-layer2.webp"
    },
    "layer3": {
      "answer": "蜻蜓点水是雌蜻蜓的产卵行为。卵产在水中或水生植物上，孵化出的幼虫叫水虿，在水中生活数月至数年，用直肠鳃呼吸，捕食孑孓等。成熟后爬出水面蜕皮，羽化为成虫。",
      "image": "images/animals/animals-2075-layer3.webp"
    },
    "science": "蜻蜓为半变态昆虫，一生经历卵→稚虫（水虿）→成虫三个阶段。水虿用可伸缩的下唇（脸盖）捕捉猎物，直肠鳃兼具呼吸和喷射推进功能。点水产卵方式分散了后代，降低被天敌一网打尽的风险。",
    "scienceImage": "images/animals/animals-2075-science.webp",
    "experiment": {
      "name": "为什么蜻蜓会点水？·小实验",
      "steps": [
        "夏天去池塘边观察蜻蜓点水，记录它一分钟点了几次水。回家画一幅\"蜻蜓的一生\"四格画：卵→水虿→爬出水面→蜻蜓。"
      ],
      "materials": [
        "纸",
        "画笔"
      ],
      "image": "images/animals/animals-2075-experiment.webp",
      "sayToChild": "",
      "duration": "约5分钟",
      "safetyNote": "需家长全程陪同",
      "experimentType": "观察"
    },
    "ipScene": "问问兔指着池塘上飞来飞去的蜻蜓问\"它为什么一直用尾巴碰水？\"答答熊说\"那是蜻蜓妈妈在生宝宝！它把宝宝放进水里，宝宝在水里长大，会游泳，会抓蚊子，长大了才爬出水面变成蜻蜓。\"",
    "warmClosing": ""
  }
]